[
  {
    "week": 1,
    "playerCash": 30000000,
    "rivalAvgCash": 217026635.30849385,
    "totalSystemCash": 2200266353.0849385,
    "totalMarketSentiment": 50,
    "talentPoolSize": 2500,
    "avgTalentPrestige": 46.65,
    "activeProjects": 0,
    "completedProjects": 0,
    "retiredCount": 0,
    "bankruptcyCount": 0
  },
  {
    "week": 2,
    "playerCash": 28328846,
    "rivalAvgCash": 217814135.30849385,
    "totalSystemCash": 2206470199.0849385,
    "totalMarketSentiment": 50,
    "talentPoolSize": 2500,
    "avgTalentPrestige": 46.65,
    "activeProjects": 0,
    "completedProjects": 0,
    "retiredCount": 0,
    "bankruptcyCount": 0
  },
  {
    "week": 3,
    "playerCash": 26656326,
    "rivalAvgCash": 218589719.16849384,
    "totalSystemCash": 2212553517.6849384,
    "totalMarketSentiment": 50,
    "talentPoolSize": 2500,
    "avgTalentPrestige": 46.65,
    "activeProjects": 0,
    "completedProjects": 0,
    "retiredCount": 0,
    "bankruptcyCount": 0
  },
  {
    "week": 4,
    "playerCash": 24981544,
    "rivalAvgCash": 219353419.16849384,
    "totalSystemCash": 2218515735.6849384,
    "totalMarketSentiment": 50,
    "talentPoolSize": 2500,
    "avgTalentPrestige": 46.65,
    "activeProjects": 0,
    "completedProjects": 0,
    "retiredCount": 0,
    "bankruptcyCount": 0
  },
  {
    "week": 5,
    "playerCash": 23305152,
    "rivalAvgCash": 220105361.02849388,
    "totalSystemCash": 2224358762.284939,
    "totalMarketSentiment": 50,
    "talentPoolSize": 2500,
    "avgTalentPrestige": 46.65,
    "activeProjects": 0,
    "completedProjects": 0,
    "retiredCount": 0,
    "bankruptcyCount": 0
  },
  {
    "week": 6,
    "playerCash": 21626742,
    "rivalAvgCash": 220845756.88849384,
    "totalSystemCash": 2230084310.8849382,
    "totalMarketSentiment": 50,
    "talentPoolSize": 2500,
    "avgTalentPrestige": 46.65,
    "activeProjects": 0,
    "completedProjects": 0,
    "retiredCount": 0,
    "bankruptcyCount": 0
  },
  {
    "week": 7,
    "playerCash": 19946872,
    "rivalAvgCash": 221364723.18849388,
    "totalSystemCash": 2233594103.8849387,
    "totalMarketSentiment": 50,
    "talentPoolSize": 2500,
    "avgTalentPrestige": 46.65,
    "activeProjects": 0,
    "completedProjects": 0,
    "retiredCount": 0,
    "bankruptcyCount": 0
  },
  {
    "week": 8,
    "playerCash": 18265956,
    "rivalAvgCash": 221992788.54849386,
    "totalSystemCash": 2238193841.4849386,
    "totalMarketSentiment": 50,
    "talentPoolSize": 2500,
    "avgTalentPrestige": 46.65,
    "activeProjects": 0,
    "completedProjects": 0,
    "retiredCount": 0,
    "bankruptcyCount": 0
  },
  {
    "week": 9,
    "playerCash": 16583308,
    "rivalAvgCash": 222568770.28849387,
    "totalSystemCash": 2242271010.8849387,
    "totalMarketSentiment": 50,
    "talentPoolSize": 2500,
    "avgTalentPrestige": 46.65,
    "activeProjects": 0,
    "completedProjects": 0,
    "retiredCount": 0,
    "bankruptcyCount": 0
  },
  {
    "week": 10,
    "playerCash": 14898738,
    "rivalAvgCash": 222882950.42849383,
    "totalSystemCash": 2243728242.2849383,
    "totalMarketSentiment": 50,
    "talentPoolSize": 2500,
    "avgTalentPrestige": 46.65,
    "activeProjects": 0,
    "completedProjects": 0,
    "retiredCount": 0,
    "bankruptcyCount": 0
  },
  {
    "week": 11,
    "playerCash": 13212318,
    "rivalAvgCash": 222757043.12849385,
    "totalSystemCash": 2240782749.2849383,
    "totalMarketSentiment": 50,
    "talentPoolSize": 2500,
    "avgTalentPrestige": 46.65,
    "activeProjects": 0,
    "completedProjects": 0,
    "retiredCount": 0,
    "bankruptcyCount": 0
  },
  {
    "week": 12,
    "playerCash": 11524498,
    "rivalAvgCash": 223192051.92849383,
    "totalSystemCash": 2243445017.2849383,
    "totalMarketSentiment": 50,
    "talentPoolSize": 2500,
    "avgTalentPrestige": 46.65,
    "activeProjects": 0,
    "completedProjects": 0,
    "retiredCount": 0,
    "bankruptcyCount": 0
  },
  {
    "week": 13,
    "playerCash": 9835242,
    "rivalAvgCash": 223584740.14849386,
    "totalSystemCash": 2245682643.4849386,
    "totalMarketSentiment": 50,
    "talentPoolSize": 2500,
    "avgTalentPrestige": 46.65,
    "activeProjects": 0,
    "completedProjects": 0,
    "retiredCount": 0,
    "bankruptcyCount": 0
  },
  {
    "week": 14,
    "playerCash": 8144464,
    "rivalAvgCash": 223937204.9484938,
    "totalSystemCash": 2247516513.484938,
    "totalMarketSentiment": 50,
    "talentPoolSize": 2500,
    "avgTalentPrestige": 46.65,
    "activeProjects": 0,
    "completedProjects": 0,
    "retiredCount": 0,
    "bankruptcyCount": 0
  },
  {
    "week": 15,
    "playerCash": 6452126,
    "rivalAvgCash": 224251302.68849382,
    "totalSystemCash": 2248965152.8849382,
    "totalMarketSentiment": 50,
    "talentPoolSize": 2500,
    "avgTalentPrestige": 46.65,
    "activeProjects": 0,
    "completedProjects": 0,
    "retiredCount": 0,
    "bankruptcyCount": 0
  },
  {
    "week": 16,
    "playerCash": 4758164,
    "rivalAvgCash": 224529048.06849384,
    "totalSystemCash": 2250048644.6849384,
    "totalMarketSentiment": 50,
    "talentPoolSize": 2500,
    "avgTalentPrestige": 46.65,
    "activeProjects": 0,
    "completedProjects": 0,
    "retiredCount": 0,
    "bankruptcyCount": 0
  },
  {
    "week": 17,
    "playerCash": 3062622,
    "rivalAvgCash": 224772313.78849387,
    "totalSystemCash": 2250785759.8849387,
    "totalMarketSentiment": 50,
    "talentPoolSize": 2500,
    "avgTalentPrestige": 46.65,
    "activeProjects": 0,
    "completedProjects": 0,
    "retiredCount": 0,
    "bankruptcyCount": 0
  },
  {
    "week": 18,
    "playerCash": 1365484,
    "rivalAvgCash": 224982853.00849384,
    "totalSystemCash": 2251194014.0849385,
    "totalMarketSentiment": 50,
    "talentPoolSize": 2500,
    "avgTalentPrestige": 46.65,
    "activeProjects": 0,
    "completedProjects": 0,
    "retiredCount": 0,
    "bankruptcyCount": 0
  },
  {
    "week": 19,
    "playerCash": -333262,
    "rivalAvgCash": 225162256.92849383,
    "totalSystemCash": 2251289307.2849383,
    "totalMarketSentiment": 50,
    "talentPoolSize": 2500,
    "avgTalentPrestige": 46.65,
    "activeProjects": 0,
    "completedProjects": 0,
    "retiredCount": 0,
    "bankruptcyCount": 0
  },
  {
    "week": 20,
    "playerCash": -2034856,
    "rivalAvgCash": 225312107.86849385,
    "totalSystemCash": 2251086222.6849384,
    "totalMarketSentiment": 50,
    "talentPoolSize": 2500,
    "avgTalentPrestige": 46.65,
    "activeProjects": 0,
    "completedProjects": 0,
    "retiredCount": 0,
    "bankruptcyCount": 0
  },
  {
    "week": 21,
    "playerCash": -3744620,
    "rivalAvgCash": 225433830.58849382,
    "totalSystemCash": 2250593685.8849382,
    "totalMarketSentiment": 50,
    "talentPoolSize": 2500,
    "avgTalentPrestige": 46.65,
    "activeProjects": 0,
    "completedProjects": 0,
    "retiredCount": 0,
    "bankruptcyCount": 0
  },
  {
    "week": 22,
    "playerCash": -5462502,
    "rivalAvgCash": 225528856.04849386,
    "totalSystemCash": 2249826058.4849386,
    "totalMarketSentiment": 50,
    "talentPoolSize": 2500,
    "avgTalentPrestige": 46.65,
    "activeProjects": 0,
    "completedProjects": 0,
    "retiredCount": 0,
    "bankruptcyCount": 0
  },
  {
    "week": 23,
    "playerCash": -7188616,
    "rivalAvgCash": 225598508.56849384,
    "totalSystemCash": 2248796469.6849384,
    "totalMarketSentiment": 50,
    "talentPoolSize": 2500,
    "avgTalentPrestige": 46.65,
    "activeProjects": 0,
    "completedProjects": 0,
    "retiredCount": 0,
    "bankruptcyCount": 0
  },
  {
    "week": 24,
    "playerCash": -8922922,
    "rivalAvgCash": 222095164.20849386,
    "totalSystemCash": 2212028720.0849385,
    "totalMarketSentiment": 50,
    "talentPoolSize": 2500,
    "avgTalentPrestige": 46.65,
    "activeProjects": 0,
    "completedProjects": 0,
    "retiredCount": 0,
    "bankruptcyCount": 0
  },
  {
    "week": 25,
    "playerCash": -10665332,
    "rivalAvgCash": 222010321.03349385,
    "totalSystemCash": 2209437878.3349385,
    "totalMarketSentiment": 50,
    "talentPoolSize": 2500,
    "avgTalentPrestige": 46.65,
    "activeProjects": 0,
    "completedProjects": 0,
    "retiredCount": 0,
    "bankruptcyCount": 0
  },
  {
    "week": 26,
    "playerCash": -12416158,
    "rivalAvgCash": 221901993.87849385,
    "totalSystemCash": 2206603780.7849383,
    "totalMarketSentiment": 50,
    "talentPoolSize": 2500,
    "avgTalentPrestige": 46.65,
    "activeProjects": 0,
    "completedProjects": 0,
    "retiredCount": 0,
    "bankruptcyCount": 0
  },
  {
    "week": 27,
    "playerCash": -14175314,
    "rivalAvgCash": 221771420.16349387,
    "totalSystemCash": 2203538887.6349387,
    "totalMarketSentiment": 50,
    "talentPoolSize": 2500,
    "avgTalentPrestige": 46.65,
    "activeProjects": 0,
    "completedProjects": 0,
    "retiredCount": 0,
    "bankruptcyCount": 0
  },
  {
    "week": 28,
    "playerCash": -15943184,
    "rivalAvgCash": 221619844.62849385,
    "totalSystemCash": 2200255262.2849383,
    "totalMarketSentiment": 50,
    "talentPoolSize": 2500,
    "avgTalentPrestige": 46.65,
    "activeProjects": 0,
    "completedProjects": 0,
    "retiredCount": 0,
    "bankruptcyCount": 0
  },
  {
    "week": 29,
    "playerCash": -17719366,
    "rivalAvgCash": 221448419.75349385,
    "totalSystemCash": 2196764831.5349383,
    "totalMarketSentiment": 50,
    "talentPoolSize": 2500,
    "avgTalentPrestige": 46.65,
    "activeProjects": 0,
    "completedProjects": 0,
    "retiredCount": 0,
    "bankruptcyCount": 0
  },
  {
    "week": 30,
    "playerCash": -19503992,
    "rivalAvgCash": 221258183.39849383,
    "totalSystemCash": 2193077841.984938,
    "totalMarketSentiment": 50,
    "talentPoolSize": 2500,
    "avgTalentPrestige": 46.65,
    "activeProjects": 0,
    "completedProjects": 0,
    "retiredCount": 0,
    "bankruptcyCount": 0
  },
  {
    "week": 31,
    "playerCash": -21296708,
    "rivalAvgCash": 221050136.86349386,
    "totalSystemCash": 2189204660.6349387,
    "totalMarketSentiment": 50,
    "talentPoolSize": 2500,
    "avgTalentPrestige": 46.65,
    "activeProjects": 0,
    "completedProjects": 0,
    "retiredCount": 0,
    "bankruptcyCount": 0
  },
  {
    "week": 32,
    "playerCash": -23098212,
    "rivalAvgCash": 220825214.7884938,
    "totalSystemCash": 2185153935.8849382,
    "totalMarketSentiment": 50,
    "talentPoolSize": 2500,
    "avgTalentPrestige": 46.65,
    "activeProjects": 0,
    "completedProjects": 0,
    "retiredCount": 0,
    "bankruptcyCount": 0
  },
  {
    "week": 33,
    "playerCash": -24908854,
    "rivalAvgCash": 220584362.57349387,
    "totalSystemCash": 2180934771.7349386,
    "totalMarketSentiment": 50,
    "talentPoolSize": 2500,
    "avgTalentPrestige": 46.65,
    "activeProjects": 0,
    "completedProjects": 0,
    "retiredCount": 0,
    "bankruptcyCount": 0
  },
  {
    "week": 34,
    "playerCash": -26728786,
    "rivalAvgCash": 220328369.85849386,
    "totalSystemCash": 2176554912.5849385,
    "totalMarketSentiment": 50,
    "talentPoolSize": 2500,
    "avgTalentPrestige": 46.65,
    "activeProjects": 0,
    "completedProjects": 0,
    "retiredCount": 0,
    "bankruptcyCount": 0
  },
  {
    "week": 35,
    "playerCash": -28557300,
    "rivalAvgCash": 220058054.56349382,
    "totalSystemCash": 2172023245.6349382,
    "totalMarketSentiment": 50,
    "talentPoolSize": 2500,
    "avgTalentPrestige": 46.65,
    "activeProjects": 0,
    "completedProjects": 0,
    "retiredCount": 0,
    "bankruptcyCount": 0
  },
  {
    "week": 36,
    "playerCash": -30394598,
    "rivalAvgCash": 219774139.76849383,
    "totalSystemCash": 2167346799.6849384,
    "totalMarketSentiment": 50,
    "talentPoolSize": 2500,
    "avgTalentPrestige": 46.65,
    "activeProjects": 0,
    "completedProjects": 0,
    "retiredCount": 0,
    "bankruptcyCount": 0
  },
  {
    "week": 37,
    "playerCash": -32240758,
    "rivalAvgCash": 219477340.83349386,
    "totalSystemCash": 2162532650.3349385,
    "totalMarketSentiment": 50,
    "talentPoolSize": 2500,
    "avgTalentPrestige": 46.65,
    "activeProjects": 0,
    "completedProjects": 0,
    "retiredCount": 0,
    "bankruptcyCount": 0
  },
  {
    "week": 38,
    "playerCash": -34095786,
    "rivalAvgCash": 219168357.2184938,
    "totalSystemCash": 2157587786.184938,
    "totalMarketSentiment": 50,
    "talentPoolSize": 2500,
    "avgTalentPrestige": 46.65,
    "activeProjects": 0,
    "completedProjects": 0,
    "retiredCount": 0,
    "bankruptcyCount": 0
  },
  {
    "week": 39,
    "playerCash": -35959692,
    "rivalAvgCash": 218847823.20349383,
    "totalSystemCash": 2152518540.0349383,
    "totalMarketSentiment": 50,
    "talentPoolSize": 2500,
    "avgTalentPrestige": 46.65,
    "activeProjects": 0,
    "completedProjects": 0,
    "retiredCount": 0,
    "bankruptcyCount": 0
  },
  {
    "week": 40,
    "playerCash": -37831896,
    "rivalAvgCash": 218516329.38849387,
    "totalSystemCash": 2147331397.8849387,
    "totalMarketSentiment": 50,
    "talentPoolSize": 2500,
    "avgTalentPrestige": 46.65,
    "activeProjects": 0,
    "completedProjects": 0,
    "retiredCount": 0,
    "bankruptcyCount": 0
  },
  {
    "week": 41,
    "playerCash": -39712172,
    "rivalAvgCash": 218174456.27349383,
    "totalSystemCash": 2142032390.7349381,
    "totalMarketSentiment": 50,
    "talentPoolSize": 2500,
    "avgTalentPrestige": 46.65,
    "activeProjects": 0,
    "completedProjects": 0,
    "retiredCount": 0,
    "bankruptcyCount": 0
  },
  {
    "week": 42,
    "playerCash": -41600692,
    "rivalAvgCash": 217822722.4384938,
    "totalSystemCash": 2136626532.3849378,
    "totalMarketSentiment": 50,
    "talentPoolSize": 2500,
    "avgTalentPrestige": 46.65,
    "activeProjects": 0,
    "completedProjects": 0,
    "retiredCount": 0,
    "bankruptcyCount": 0
  },
  {
    "week": 43,
    "playerCash": -43498274,
    "rivalAvgCash": 217461654.72349387,
    "totalSystemCash": 2131118273.2349386,
    "totalMarketSentiment": 50,
    "talentPoolSize": 2500,
    "avgTalentPrestige": 46.65,
    "activeProjects": 0,
    "completedProjects": 0,
    "retiredCount": 0,
    "bankruptcyCount": 0
  },
  {
    "week": 44,
    "playerCash": -45405844,
    "rivalAvgCash": 217091712.66849384,
    "totalSystemCash": 2125511282.6849384,
    "totalMarketSentiment": 50,
    "talentPoolSize": 2500,
    "avgTalentPrestige": 46.65,
    "activeProjects": 0,
    "completedProjects": 0,
    "retiredCount": 0,
    "bankruptcyCount": 0
  },
  {
    "week": 45,
    "playerCash": -47322196,
    "rivalAvgCash": 216713373.21349388,
    "totalSystemCash": 2119811536.1349387,
    "totalMarketSentiment": 50,
    "talentPoolSize": 2500,
    "avgTalentPrestige": 46.65,
    "activeProjects": 0,
    "completedProjects": 0,
    "retiredCount": 0,
    "bankruptcyCount": 0
  },
  {
    "week": 46,
    "playerCash": -49248984,
    "rivalAvgCash": 216327068.35849386,
    "totalSystemCash": 2114021699.5849385,
    "totalMarketSentiment": 50,
    "talentPoolSize": 2500,
    "avgTalentPrestige": 46.65,
    "activeProjects": 0,
    "completedProjects": 0,
    "retiredCount": 0,
    "bankruptcyCount": 0
  },
  {
    "week": 47,
    "playerCash": -51183622,
    "rivalAvgCash": 215933186.40349382,
    "totalSystemCash": 2108148242.0349383,
    "totalMarketSentiment": 50,
    "talentPoolSize": 2500,
    "avgTalentPrestige": 46.65,
    "activeProjects": 0,
    "completedProjects": 0,
    "retiredCount": 0,
    "bankruptcyCount": 0
  },
  {
    "week": 48,
    "playerCash": -53127544,
    "rivalAvgCash": 215532123.08849382,
    "totalSystemCash": 2102193686.8849382,
    "totalMarketSentiment": 50,
    "talentPoolSize": 2500,
    "avgTalentPrestige": 46.65,
    "activeProjects": 0,
    "completedProjects": 0,
    "retiredCount": 0,
    "bankruptcyCount": 0
  },
  {
    "week": 49,
    "playerCash": -55081396,
    "rivalAvgCash": 215124251.75349385,
    "totalSystemCash": 2096161121.5349383,
    "totalMarketSentiment": 50,
    "talentPoolSize": 2500,
    "avgTalentPrestige": 46.65,
    "activeProjects": 0,
    "completedProjects": 0,
    "retiredCount": 0,
    "bankruptcyCount": 0
  },
  {
    "week": 50,
    "playerCash": -57043634,
    "rivalAvgCash": 214709919.07849383,
    "totalSystemCash": 2090055556.7849383,
    "totalMarketSentiment": 50,
    "talentPoolSize": 2500,
    "avgTalentPrestige": 46.65,
    "activeProjects": 0,
    "completedProjects": 0,
    "retiredCount": 0,
    "bankruptcyCount": 0
  },
  {
    "week": 51,
    "playerCash": -59016384,
    "rivalAvgCash": 214289447.24349383,
    "totalSystemCash": 2083878088.4349382,
    "totalMarketSentiment": 50,
    "talentPoolSize": 2500,
    "avgTalentPrestige": 46.65,
    "activeProjects": 0,
    "completedProjects": 0,
    "retiredCount": 0,
    "bankruptcyCount": 0
  },
  {
    "week": 52,
    "playerCash": -60999366,
    "rivalAvgCash": 213863163.08849382,
    "totalSystemCash": 2077632264.8849382,
    "totalMarketSentiment": 50,
    "talentPoolSize": 2500,
    "avgTalentPrestige": 46.65,
    "activeProjects": 0,
    "completedProjects": 0,
    "retiredCount": 0,
    "bankruptcyCount": 0
  },
  {
    "week": 53,
    "playerCash": -62990128,
    "rivalAvgCash": 213431349.4134938,
    "totalSystemCash": 2071323366.1349382,
    "totalMarketSentiment": 50,
    "talentPoolSize": 2500,
    "avgTalentPrestige": 46.65,
    "activeProjects": 0,
    "completedProjects": 0,
    "retiredCount": 0,
    "bankruptcyCount": 0
  },
  {
    "week": 54,
    "playerCash": -64991530,
    "rivalAvgCash": 212994296.27849382,
    "totalSystemCash": 2064951432.784938,
    "totalMarketSentiment": 50,
    "talentPoolSize": 2500,
    "avgTalentPrestige": 46.6444,
    "activeProjects": 0,
    "completedProjects": 0,
    "retiredCount": 1,
    "bankruptcyCount": 0
  },
  {
    "week": 55,
    "playerCash": -67000816,
    "rivalAvgCash": 212552255.56349382,
    "totalSystemCash": 2058521739.6349382,
    "totalMarketSentiment": 50,
    "talentPoolSize": 2500,
    "avgTalentPrestige": 46.6444,
    "activeProjects": 0,
    "completedProjects": 0,
    "retiredCount": 1,
    "bankruptcyCount": 0
  },
  {
    "week": 56,
    "playerCash": -69018758,
    "rivalAvgCash": 212105475.8084938,
    "totalSystemCash": 2052036000.084938,
    "totalMarketSentiment": 50,
    "talentPoolSize": 2500,
    "avgTalentPrestige": 46.6408,
    "activeProjects": 0,
    "completedProjects": 0,
    "retiredCount": 2,
    "bankruptcyCount": 0
  },
  {
    "week": 57,
    "playerCash": -71047226,
    "rivalAvgCash": 211654201.75349385,
    "totalSystemCash": 2045494791.5349386,
    "totalMarketSentiment": 50,
    "talentPoolSize": 2500,
    "avgTalentPrestige": 46.6408,
    "activeProjects": 0,
    "completedProjects": 0,
    "retiredCount": 2,
    "bankruptcyCount": 0
  },
  {
    "week": 58,
    "playerCash": -73083596,
    "rivalAvgCash": 211198665.09849384,
    "totalSystemCash": 2038903054.9849384,
    "totalMarketSentiment": 50,
    "talentPoolSize": 2500,
    "avgTalentPrestige": 46.6408,
    "activeProjects": 0,
    "completedProjects": 0,
    "retiredCount": 2,
    "bankruptcyCount": 0
  },
  {
    "week": 59,
    "playerCash": -75129438,
    "rivalAvgCash": 210739087.34349385,
    "totalSystemCash": 2032261435.4349384,
    "totalMarketSentiment": 50,
    "talentPoolSize": 2500,
    "avgTalentPrestige": 46.6484,
    "activeProjects": 0,
    "completedProjects": 0,
    "retiredCount": 3,
    "bankruptcyCount": 0
  },
  {
    "week": 60,
    "playerCash": -77185218,
    "rivalAvgCash": 210275669.04849383,
    "totalSystemCash": 2025571472.4849384,
    "totalMarketSentiment": 50,
    "talentPoolSize": 2500,
    "avgTalentPrestige": 46.6484,
    "activeProjects": 0,
    "completedProjects": 0,
    "retiredCount": 3,
    "bankruptcyCount": 0
  },
  {
    "week": 61,
    "playerCash": -79248538,
    "rivalAvgCash": 209808612.39349383,
    "totalSystemCash": 2018837585.9349384,
    "totalMarketSentiment": 50,
    "talentPoolSize": 2500,
    "avgTalentPrestige": 46.6484,
    "activeProjects": 0,
    "completedProjects": 0,
    "retiredCount": 3,
    "bankruptcyCount": 0
  },
  {
    "week": 62,
    "playerCash": -81321798,
    "rivalAvgCash": 209338092.21849385,
    "totalSystemCash": 2012059124.1849384,
    "totalMarketSentiment": 50,
    "talentPoolSize": 2500,
    "avgTalentPrestige": 46.6484,
    "activeProjects": 0,
    "completedProjects": 0,
    "retiredCount": 3,
    "bankruptcyCount": 0
  },
  {
    "week": 63,
    "playerCash": -83406034,
    "rivalAvgCash": 208864289.3234938,
    "totalSystemCash": 2005236859.2349381,
    "totalMarketSentiment": 50,
    "talentPoolSize": 2500,
    "avgTalentPrestige": 46.6484,
    "activeProjects": 0,
    "completedProjects": 0,
    "retiredCount": 3,
    "bankruptcyCount": 0
  },
  {
    "week": 64,
    "playerCash": -85499606,
    "rivalAvgCash": 208387362.38849384,
    "totalSystemCash": 1998374017.8849385,
    "totalMarketSentiment": 50,
    "talentPoolSize": 2500,
    "avgTalentPrestige": 46.6484,
    "activeProjects": 0,
    "completedProjects": 0,
    "retiredCount": 3,
    "bankruptcyCount": 0
  },
  {
    "week": 65,
    "playerCash": -87602436,
    "rivalAvgCash": 207907472.85349384,
    "totalSystemCash": 1991472292.5349383,
    "totalMarketSentiment": 50,
    "talentPoolSize": 2500,
    "avgTalentPrestige": 46.6484,
    "activeProjects": 0,
    "completedProjects": 0,
    "retiredCount": 3,
    "bankruptcyCount": 0
  },
  {
    "week": 66,
    "playerCash": -89716304,
    "rivalAvgCash": 207424770.57849383,
    "totalSystemCash": 1984531401.7849383,
    "totalMarketSentiment": 50,
    "talentPoolSize": 2500,
    "avgTalentPrestige": 46.6484,
    "activeProjects": 0,
    "completedProjects": 0,
    "retiredCount": 3,
    "bankruptcyCount": 0
  },
  {
    "week": 67,
    "playerCash": -91839586,
    "rivalAvgCash": 206939389.28349385,
    "totalSystemCash": 1977554306.8349385,
    "totalMarketSentiment": 50,
    "talentPoolSize": 2500,
    "avgTalentPrestige": 46.6548,
    "activeProjects": 0,
    "completedProjects": 0,
    "retiredCount": 4,
    "bankruptcyCount": 0
  },
  {
    "week": 68,
    "playerCash": -93972922,
    "rivalAvgCash": 206451467.70849386,
    "totalSystemCash": 1970541755.0849385,
    "totalMarketSentiment": 50,
    "talentPoolSize": 2500,
    "avgTalentPrestige": 46.6548,
    "activeProjects": 0,
    "completedProjects": 0,
    "retiredCount": 4,
    "bankruptcyCount": 0
  },
  {
    "week": 69,
    "playerCash": -96117258,
    "rivalAvgCash": 205961127.85349384,
    "totalSystemCash": 1963494020.5349383,
    "totalMarketSentiment": 50,
    "talentPoolSize": 2500,
    "avgTalentPrestige": 46.6548,
    "activeProjects": 0,
    "completedProjects": 0,
    "retiredCount": 4,
    "bankruptcyCount": 0
  },
  {
    "week": 70,
    "playerCash": -98274406,
    "rivalAvgCash": 205468499.35849383,
    "totalSystemCash": 1956410587.5849383,
    "totalMarketSentiment": 50,
    "talentPoolSize": 2500,
    "avgTalentPrestige": 46.6548,
    "activeProjects": 0,
    "completedProjects": 0,
    "retiredCount": 4,
    "bankruptcyCount": 0
  },
  {
    "week": 71,
    "playerCash": -100444350,
    "rivalAvgCash": 204973691.9434938,
    "totalSystemCash": 1949292569.4349382,
    "totalMarketSentiment": 50,
    "talentPoolSize": 2500,
    "avgTalentPrestige": 46.6548,
    "activeProjects": 0,
    "completedProjects": 0,
    "retiredCount": 4,
    "bankruptcyCount": 0
  },
  {
    "week": 72,
    "playerCash": -102622806,
    "rivalAvgCash": 204476819.3484938,
    "totalSystemCash": 1942145387.4849381,
    "totalMarketSentiment": 50,
    "talentPoolSize": 2500,
    "avgTalentPrestige": 46.6548,
    "activeProjects": 0,
    "completedProjects": 0,
    "retiredCount": 4,
    "bankruptcyCount": 0
  },
  {
    "week": 73,
    "playerCash": -104812208,
    "rivalAvgCash": 203977983.21349382,
    "totalSystemCash": 1934967624.1349382,
    "totalMarketSentiment": 50,
    "talentPoolSize": 2500,
    "avgTalentPrestige": 46.6508,
    "activeProjects": 0,
    "completedProjects": 0,
    "retiredCount": 5,
    "bankruptcyCount": 0
  },
  {
    "week": 74,
    "playerCash": -107010244,
    "rivalAvgCash": 203477288.33849385,
    "totalSystemCash": 1927762639.3849385,
    "totalMarketSentiment": 50,
    "talentPoolSize": 2500,
    "avgTalentPrestige": 46.6508,
    "activeProjects": 0,
    "completedProjects": 0,
    "retiredCount": 5,
    "bankruptcyCount": 0
  },
  {
    "week": 75,
    "playerCash": -109221694,
    "rivalAvgCash": 202974820.56349382,
    "totalSystemCash": 1920526511.6349382,
    "totalMarketSentiment": 50,
    "talentPoolSize": 2500,
    "avgTalentPrestige": 46.6508,
    "activeProjects": 0,
    "completedProjects": 0,
    "retiredCount": 5,
    "bankruptcyCount": 0
  },
  {
    "week": 76,
    "playerCash": -111443110,
    "rivalAvgCash": 202470672.48849383,
    "totalSystemCash": 1913263614.8849382,
    "totalMarketSentiment": 50,
    "talentPoolSize": 2500,
    "avgTalentPrestige": 46.64,
    "activeProjects": 0,
    "completedProjects": 0,
    "retiredCount": 6,
    "bankruptcyCount": 0
  },
  {
    "week": 77,
    "playerCash": -113675026,
    "rivalAvgCash": 201964927.19349384,
    "totalSystemCash": 1905974245.9349384,
    "totalMarketSentiment": 50,
    "talentPoolSize": 2500,
    "avgTalentPrestige": 46.64,
    "activeProjects": 0,
    "completedProjects": 0,
    "retiredCount": 6,
    "bankruptcyCount": 0
  },
  {
    "week": 78,
    "playerCash": -115917966,
    "rivalAvgCash": 201457669.95849386,
    "totalSystemCash": 1898658733.5849385,
    "totalMarketSentiment": 50,
    "talentPoolSize": 2500,
    "avgTalentPrestige": 46.64,
    "activeProjects": 0,
    "completedProjects": 0,
    "retiredCount": 6,
    "bankruptcyCount": 0
  },
  {
    "week": 79,
    "playerCash": -118172972,
    "rivalAvgCash": 200948974.92349386,
    "totalSystemCash": 1891316777.2349386,
    "totalMarketSentiment": 50,
    "talentPoolSize": 2500,
    "avgTalentPrestige": 46.64,
    "activeProjects": 0,
    "completedProjects": 0,
    "retiredCount": 6,
    "bankruptcyCount": 0
  },
  {
    "week": 80,
    "playerCash": -120441170,
    "rivalAvgCash": 200438911.3484938,
    "totalSystemCash": 1883947943.4849381,
    "totalMarketSentiment": 50,
    "talentPoolSize": 2500,
    "avgTalentPrestige": 46.64,
    "activeProjects": 0,
    "completedProjects": 0,
    "retiredCount": 6,
    "bankruptcyCount": 0
  },
  {
    "week": 81,
    "playerCash": -122721732,
    "rivalAvgCash": 199927547.65349382,
    "totalSystemCash": 1876553744.5349383,
    "totalMarketSentiment": 50,
    "talentPoolSize": 2500,
    "avgTalentPrestige": 46.64,
    "activeProjects": 0,
    "completedProjects": 0,
    "retiredCount": 6,
    "bankruptcyCount": 0
  },
  {
    "week": 82,
    "playerCash": -125011574,
    "rivalAvgCash": 199414949.87849385,
    "totalSystemCash": 1869137924.7849383,
    "totalMarketSentiment": 50,
    "talentPoolSize": 2500,
    "avgTalentPrestige": 46.64,
    "activeProjects": 0,
    "completedProjects": 0,
    "retiredCount": 6,
    "bankruptcyCount": 0
  },
  {
    "week": 83,
    "playerCash": -127309046,
    "rivalAvgCash": 198901179.50349385,
    "totalSystemCash": 1861702749.0349383,
    "totalMarketSentiment": 50,
    "talentPoolSize": 2500,
    "avgTalentPrestige": 46.64,
    "activeProjects": 0,
    "completedProjects": 0,
    "retiredCount": 6,
    "bankruptcyCount": 0
  },
  {
    "week": 84,
    "playerCash": -129618504,
    "rivalAvgCash": 198386295.40849385,
    "totalSystemCash": 1854244450.0849385,
    "totalMarketSentiment": 50,
    "talentPoolSize": 2500,
    "avgTalentPrestige": 46.64,
    "activeProjects": 0,
    "completedProjects": 0,
    "retiredCount": 6,
    "bankruptcyCount": 0
  },
  {
    "week": 85,
    "playerCash": -131942188,
    "rivalAvgCash": 197870351.1334938,
    "totalSystemCash": 1846761323.334938,
    "totalMarketSentiment": 50,
    "talentPoolSize": 2500,
    "avgTalentPrestige": 46.64,
    "activeProjects": 0,
    "completedProjects": 0,
    "retiredCount": 6,
    "bankruptcyCount": 0
  },
  {
    "week": 86,
    "playerCash": -134277904,
    "rivalAvgCash": 197353404.0384938,
    "totalSystemCash": 1839256136.3849382,
    "totalMarketSentiment": 50,
    "talentPoolSize": 2500,
    "avgTalentPrestige": 46.64,
    "activeProjects": 0,
    "completedProjects": 0,
    "retiredCount": 6,
    "bankruptcyCount": 0
  },
  {
    "week": 87,
    "playerCash": -136624020,
    "rivalAvgCash": 196835504.56349382,
    "totalSystemCash": 1831731025.6349382,
    "totalMarketSentiment": 50,
    "talentPoolSize": 2500,
    "avgTalentPrestige": 46.64,
    "activeProjects": 0,
    "completedProjects": 0,
    "retiredCount": 6,
    "bankruptcyCount": 0
  },
  {
    "week": 88,
    "playerCash": -138978536,
    "rivalAvgCash": 196316699.50849384,
    "totalSystemCash": 1824188459.0849383,
    "totalMarketSentiment": 50,
    "talentPoolSize": 2500,
    "avgTalentPrestige": 46.64,
    "activeProjects": 0,
    "completedProjects": 0,
    "retiredCount": 6,
    "bankruptcyCount": 0
  },
  {
    "week": 89,
    "playerCash": -141341708,
    "rivalAvgCash": 195797030.37349385,
    "totalSystemCash": 1816628595.7349384,
    "totalMarketSentiment": 50,
    "talentPoolSize": 2500,
    "avgTalentPrestige": 46.64,
    "activeProjects": 0,
    "completedProjects": 0,
    "retiredCount": 6,
    "bankruptcyCount": 0
  },
  {
    "week": 90,
    "playerCash": -143714216,
    "rivalAvgCash": 195276543.0984938,
    "totalSystemCash": 1809051214.9849381,
    "totalMarketSentiment": 50,
    "talentPoolSize": 2500,
    "avgTalentPrestige": 46.64,
    "activeProjects": 0,
    "completedProjects": 0,
    "retiredCount": 6,
    "bankruptcyCount": 0
  },
  {
    "week": 91,
    "playerCash": -146100908,
    "rivalAvgCash": 194755278.48349383,
    "totalSystemCash": 1801451876.8349383,
    "totalMarketSentiment": 50,
    "talentPoolSize": 2500,
    "avgTalentPrestige": 46.64,
    "activeProjects": 0,
    "completedProjects": 0,
    "retiredCount": 6,
    "bankruptcyCount": 0
  },
  {
    "week": 92,
    "playerCash": -148495216,
    "rivalAvgCash": 194233276.7084938,
    "totalSystemCash": 1793837551.084938,
    "totalMarketSentiment": 50,
    "talentPoolSize": 2500,
    "avgTalentPrestige": 46.64,
    "activeProjects": 0,
    "completedProjects": 0,
    "retiredCount": 6,
    "bankruptcyCount": 0
  },
  {
    "week": 93,
    "playerCash": -150903168,
    "rivalAvgCash": 193710573.59349385,
    "totalSystemCash": 1786202567.9349384,
    "totalMarketSentiment": 50,
    "talentPoolSize": 2500,
    "avgTalentPrestige": 46.64,
    "activeProjects": 0,
    "completedProjects": 0,
    "retiredCount": 6,
    "bankruptcyCount": 0
  },
  {
    "week": 94,
    "playerCash": -153319538,
    "rivalAvgCash": 193187203.29849383,
    "totalSystemCash": 1778552494.9849384,
    "totalMarketSentiment": 50,
    "talentPoolSize": 2500,
    "avgTalentPrestige": 46.64,
    "activeProjects": 0,
    "completedProjects": 0,
    "retiredCount": 6,
    "bankruptcyCount": 0
  },
  {
    "week": 95,
    "playerCash": -155747202,
    "rivalAvgCash": 192663199.56349385,
    "totalSystemCash": 1770884793.6349385,
    "totalMarketSentiment": 50,
    "talentPoolSize": 2500,
    "avgTalentPrestige": 46.64,
    "activeProjects": 0,
    "completedProjects": 0,
    "retiredCount": 6,
    "bankruptcyCount": 0
  },
  {
    "week": 96,
    "playerCash": -158188138,
    "rivalAvgCash": 192138594.46849385,
    "totalSystemCash": 1763197806.6849384,
    "totalMarketSentiment": 50,
    "talentPoolSize": 2500,
    "avgTalentPrestige": 46.64,
    "activeProjects": 0,
    "completedProjects": 0,
    "retiredCount": 6,
    "bankruptcyCount": 0
  },
  {
    "week": 97,
    "playerCash": -160636152,
    "rivalAvgCash": 191613418.13349384,
    "totalSystemCash": 1755498029.3349383,
    "totalMarketSentiment": 50,
    "talentPoolSize": 2500,
    "avgTalentPrestige": 46.64,
    "activeProjects": 0,
    "completedProjects": 0,
    "retiredCount": 6,
    "bankruptcyCount": 0
  },
  {
    "week": 98,
    "playerCash": -163091920,
    "rivalAvgCash": 191087699.09849384,
    "totalSystemCash": 1747785070.9849384,
    "totalMarketSentiment": 50,
    "talentPoolSize": 2500,
    "avgTalentPrestige": 46.64,
    "activeProjects": 0,
    "completedProjects": 0,
    "retiredCount": 6,
    "bankruptcyCount": 0
  },
  {
    "week": 99,
    "playerCash": -165555388,
    "rivalAvgCash": 190561465.04349384,
    "totalSystemCash": 1740059262.4349384,
    "totalMarketSentiment": 50,
    "talentPoolSize": 2500,
    "avgTalentPrestige": 46.64,
    "activeProjects": 0,
    "completedProjects": 0,
    "retiredCount": 6,
    "bankruptcyCount": 0
  },
  {
    "week": 100,
    "playerCash": -168029210,
    "rivalAvgCash": 190034741.4284938,
    "totalSystemCash": 1732318204.284938,
    "totalMarketSentiment": 50,
    "talentPoolSize": 2500,
    "avgTalentPrestige": 46.64,
    "activeProjects": 0,
    "completedProjects": 0,
    "retiredCount": 6,
    "bankruptcyCount": 0
  },
  {
    "week": 101,
    "playerCash": -170513004,
    "rivalAvgCash": 189507552.4134938,
    "totalSystemCash": 1724562520.1349382,
    "totalMarketSentiment": 50,
    "talentPoolSize": 2500,
    "avgTalentPrestige": 46.64,
    "activeProjects": 0,
    "completedProjects": 0,
    "retiredCount": 6,
    "bankruptcyCount": 0
  },
  {
    "week": 102,
    "playerCash": -173010434,
    "rivalAvgCash": 188979922.61849383,
    "totalSystemCash": 1716788792.1849382,
    "totalMarketSentiment": 50,
    "talentPoolSize": 2500,
    "avgTalentPrestige": 46.64,
    "activeProjects": 0,
    "completedProjects": 0,
    "retiredCount": 6,
    "bankruptcyCount": 0
  },
  {
    "week": 103,
    "playerCash": -175520446,
    "rivalAvgCash": 188451873.04349384,
    "totalSystemCash": 1708998284.4349384,
    "totalMarketSentiment": 50,
    "talentPoolSize": 2500,
    "avgTalentPrestige": 46.64,
    "activeProjects": 0,
    "completedProjects": 0,
    "retiredCount": 6,
    "bankruptcyCount": 0
  },
  {
    "week": 104,
    "playerCash": -178044196,
    "rivalAvgCash": 187923424.2884938,
    "totalSystemCash": 1701190046.8849382,
    "totalMarketSentiment": 50,
    "talentPoolSize": 2500,
    "avgTalentPrestige": 46.64,
    "activeProjects": 0,
    "completedProjects": 0,
    "retiredCount": 6,
    "bankruptcyCount": 0
  },
  {
    "week": 105,
    "playerCash": -180582966,
    "rivalAvgCash": 187394597.33349383,
    "totalSystemCash": 1693363007.3349383,
    "totalMarketSentiment": 50,
    "talentPoolSize": 2500,
    "avgTalentPrestige": 46.6572,
    "activeProjects": 0,
    "completedProjects": 0,
    "retiredCount": 7,
    "bankruptcyCount": 0
  },
  {
    "week": 106,
    "playerCash": -183136466,
    "rivalAvgCash": 186865411.0384938,
    "totalSystemCash": 1685517644.3849382,
    "totalMarketSentiment": 50,
    "talentPoolSize": 2500,
    "avgTalentPrestige": 46.6572,
    "activeProjects": 0,
    "completedProjects": 0,
    "retiredCount": 7,
    "bankruptcyCount": 0
  },
  {
    "week": 107,
    "playerCash": -185700690,
    "rivalAvgCash": 186335883.00349385,
    "totalSystemCash": 1677658140.0349383,
    "totalMarketSentiment": 50,
    "talentPoolSize": 2500,
    "avgTalentPrestige": 46.6572,
    "activeProjects": 0,
    "completedProjects": 0,
    "retiredCount": 7,
    "bankruptcyCount": 0
  },
  {
    "week": 108,
    "playerCash": -188277594,
    "rivalAvgCash": 185806030.2884938,
    "totalSystemCash": 1669782708.8849382,
    "totalMarketSentiment": 50,
    "talentPoolSize": 2500,
    "avgTalentPrestige": 46.6556,
    "activeProjects": 0,
    "completedProjects": 0,
    "retiredCount": 8,
    "bankruptcyCount": 0
  },
  {
    "week": 109,
    "playerCash": -190867420,
    "rivalAvgCash": 185275869.03349382,
    "totalSystemCash": 1661891270.3349383,
    "totalMarketSentiment": 50,
    "talentPoolSize": 2500,
    "avgTalentPrestige": 46.6556,
    "activeProjects": 0,
    "completedProjects": 1,
    "retiredCount": 8,
    "bankruptcyCount": 0
  },
  {
    "week": 110,
    "playerCash": -193468416,
    "rivalAvgCash": 184745414.75849384,
    "totalSystemCash": 1653985731.5849383,
    "totalMarketSentiment": 50,
    "talentPoolSize": 2500,
    "avgTalentPrestige": 46.6384,
    "activeProjects": 0,
    "completedProjects": 2,
    "retiredCount": 9,
    "bankruptcyCount": 0
  },
  {
    "week": 111,
    "playerCash": -196086504,
    "rivalAvgCash": 184214682.58349383,
    "totalSystemCash": 1646060321.8349383,
    "totalMarketSentiment": 50,
    "talentPoolSize": 2500,
    "avgTalentPrestige": 46.6384,
    "activeProjects": 0,
    "completedProjects": 2,
    "retiredCount": 9,
    "bankruptcyCount": 0
  },
  {
    "week": 112,
    "playerCash": -198718774,
    "rivalAvgCash": 183683685.5084938,
    "totalSystemCash": 1638118081.084938,
    "totalMarketSentiment": 50,
    "talentPoolSize": 2500,
    "avgTalentPrestige": 46.6384,
    "activeProjects": 0,
    "completedProjects": 2,
    "retiredCount": 9,
    "bankruptcyCount": 0
  },
  {
    "week": 113,
    "playerCash": -201363658,
    "rivalAvgCash": 183152436.93349382,
    "totalSystemCash": 1630160711.3349383,
    "totalMarketSentiment": 50,
    "talentPoolSize": 2500,
    "avgTalentPrestige": 46.6384,
    "activeProjects": 0,
    "completedProjects": 2,
    "retiredCount": 9,
    "bankruptcyCount": 0
  },
  {
    "week": 114,
    "playerCash": -204020400,
    "rivalAvgCash": 182620949.33849382,
    "totalSystemCash": 1622189093.3849382,
    "totalMarketSentiment": 50,
    "talentPoolSize": 2500,
    "avgTalentPrestige": 46.6384,
    "activeProjects": 0,
    "completedProjects": 2,
    "retiredCount": 9,
    "bankruptcyCount": 0
  },
  {
    "week": 115,
    "playerCash": -206691718,
    "rivalAvgCash": 182089235.28349382,
    "totalSystemCash": 1614200634.834938,
    "totalMarketSentiment": 50,
    "talentPoolSize": 2500,
    "avgTalentPrestige": 46.6384,
    "activeProjects": 0,
    "completedProjects": 2,
    "retiredCount": 9,
    "bankruptcyCount": 0
  },
  {
    "week": 116,
    "playerCash": -209379540,
    "rivalAvgCash": 181557306.4484938,
    "totalSystemCash": 1606193524.4849381,
    "totalMarketSentiment": 50,
    "talentPoolSize": 2500,
    "avgTalentPrestige": 46.628,
    "activeProjects": 0,
    "completedProjects": 2,
    "retiredCount": 10,
    "bankruptcyCount": 0
  },
  {
    "week": 117,
    "playerCash": -212084918,
    "rivalAvgCash": 181025173.0734938,
    "totalSystemCash": 1598166812.7349381,
    "totalMarketSentiment": 50,
    "talentPoolSize": 2500,
    "avgTalentPrestige": 46.628,
    "activeProjects": 0,
    "completedProjects": 2,
    "retiredCount": 10,
    "bankruptcyCount": 0
  },
  {
    "week": 118,
    "playerCash": -214807470,
    "rivalAvgCash": 180492845.33849382,
    "totalSystemCash": 1590120983.3849382,
    "totalMarketSentiment": 50,
    "talentPoolSize": 2500,
    "avgTalentPrestige": 46.628,
    "activeProjects": 0,
    "completedProjects": 2,
    "retiredCount": 10,
    "bankruptcyCount": 0
  },
  {
    "week": 119,
    "playerCash": -217539572,
    "rivalAvgCash": 179960332.74349383,
    "totalSystemCash": 1582063755.4349382,
    "totalMarketSentiment": 50,
    "talentPoolSize": 2500,
    "avgTalentPrestige": 46.628,
    "activeProjects": 0,
    "completedProjects": 2,
    "retiredCount": 10,
    "bankruptcyCount": 0
  },
  {
    "week": 120,
    "playerCash": -220290636,
    "rivalAvgCash": 179427644.96849382,
    "totalSystemCash": 1573985813.6849382,
    "totalMarketSentiment": 50,
    "talentPoolSize": 2500,
    "avgTalentPrestige": 46.628,
    "activeProjects": 0,
    "completedProjects": 2,
    "retiredCount": 10,
    "bankruptcyCount": 0
  },
  {
    "week": 121,
    "playerCash": -223057942,
    "rivalAvgCash": 178894790.6934938,
    "totalSystemCash": 1565889964.9349382,
    "totalMarketSentiment": 50,
    "talentPoolSize": 2500,
    "avgTalentPrestige": 46.628,
    "activeProjects": 0,
    "completedProjects": 2,
    "retiredCount": 10,
    "bankruptcyCount": 0
  },
  {
    "week": 122,
    "playerCash": -225836502,
    "rivalAvgCash": 178361778.01849383,
    "totalSystemCash": 1557781278.1849384,
    "totalMarketSentiment": 50,
    "talentPoolSize": 2500,
    "avgTalentPrestige": 46.628,
    "activeProjects": 0,
    "completedProjects": 2,
    "retiredCount": 10,
    "bankruptcyCount": 0
  },
  {
    "week": 123,
    "playerCash": -228630346,
    "rivalAvgCash": 177828614.6634938,
    "totalSystemCash": 1549655800.6349382,
    "totalMarketSentiment": 50,
    "talentPoolSize": 2500,
    "avgTalentPrestige": 46.628,
    "activeProjects": 0,
    "completedProjects": 2,
    "retiredCount": 10,
    "bankruptcyCount": 0
  },
  {
    "week": 124,
    "playerCash": -231440110,
    "rivalAvgCash": 177295308.1684938,
    "totalSystemCash": 1541512971.6849382,
    "totalMarketSentiment": 50,
    "talentPoolSize": 2500,
    "avgTalentPrestige": 46.628,
    "activeProjects": 0,
    "completedProjects": 2,
    "retiredCount": 10,
    "bankruptcyCount": 0
  },
  {
    "week": 125,
    "playerCash": -234268830,
    "rivalAvgCash": 176761866.03349382,
    "totalSystemCash": 1533349830.3349383,
    "totalMarketSentiment": 50,
    "talentPoolSize": 2500,
    "avgTalentPrestige": 46.628,
    "activeProjects": 0,
    "completedProjects": 2,
    "retiredCount": 10,
    "bankruptcyCount": 0
  },
  {
    "week": 126,
    "playerCash": -237108528,
    "rivalAvgCash": 176228295.31849384,
    "totalSystemCash": 1525174425.1849384,
    "totalMarketSentiment": 50,
    "talentPoolSize": 2500,
    "avgTalentPrestige": 46.628,
    "activeProjects": 0,
    "completedProjects": 2,
    "retiredCount": 10,
    "bankruptcyCount": 0
  },
  {
    "week": 127,
    "playerCash": -239961942,
    "rivalAvgCash": 175694602.02349383,
    "totalSystemCash": 1516984078.2349381,
    "totalMarketSentiment": 50,
    "talentPoolSize": 2500,
    "avgTalentPrestige": 46.628,
    "activeProjects": 0,
    "completedProjects": 2,
    "retiredCount": 10,
    "bankruptcyCount": 0
  },
  {
    "week": 128,
    "playerCash": -242825924,
    "rivalAvgCash": 175160792.22849384,
    "totalSystemCash": 1508781998.2849383,
    "totalMarketSentiment": 50,
    "talentPoolSize": 2500,
    "avgTalentPrestige": 46.628,
    "activeProjects": 0,
    "completedProjects": 2,
    "retiredCount": 10,
    "bankruptcyCount": 0
  },
  {
    "week": 129,
    "playerCash": -245701792,
    "rivalAvgCash": 174626871.81349385,
    "totalSystemCash": 1500566926.1349385,
    "totalMarketSentiment": 50,
    "talentPoolSize": 2500,
    "avgTalentPrestige": 46.628,
    "activeProjects": 0,
    "completedProjects": 2,
    "retiredCount": 10,
    "bankruptcyCount": 0
  },
  {
    "week": 130,
    "playerCash": -248597702,
    "rivalAvgCash": 174092846.7584938,
    "totalSystemCash": 1492330765.584938,
    "totalMarketSentiment": 50,
    "talentPoolSize": 2500,
    "avgTalentPrestige": 46.628,
    "activeProjects": 0,
    "completedProjects": 2,
    "retiredCount": 10,
    "bankruptcyCount": 0
  },
  {
    "week": 131,
    "playerCash": -251513014,
    "rivalAvgCash": 173558721.78349385,
    "totalSystemCash": 1484074203.8349385,
    "totalMarketSentiment": 50,
    "talentPoolSize": 2500,
    "avgTalentPrestige": 46.628,
    "activeProjects": 0,
    "completedProjects": 2,
    "retiredCount": 10,
    "bankruptcyCount": 0
  },
  {
    "week": 132,
    "playerCash": -254441864,
    "rivalAvgCash": 173024502.00849384,
    "totalSystemCash": 1475803156.0849383,
    "totalMarketSentiment": 50,
    "talentPoolSize": 2500,
    "avgTalentPrestige": 46.628,
    "activeProjects": 0,
    "completedProjects": 2,
    "retiredCount": 10,
    "bankruptcyCount": 0
  },
  {
    "week": 133,
    "playerCash": -257380372,
    "rivalAvgCash": 172490192.17349383,
    "totalSystemCash": 1467521549.7349384,
    "totalMarketSentiment": 50,
    "talentPoolSize": 2500,
    "avgTalentPrestige": 46.628,
    "activeProjects": 0,
    "completedProjects": 2,
    "retiredCount": 10,
    "bankruptcyCount": 0
  },
  {
    "week": 134,
    "playerCash": -260325882,
    "rivalAvgCash": 171955796.9984938,
    "totalSystemCash": 1459232087.984938,
    "totalMarketSentiment": 50,
    "talentPoolSize": 2500,
    "avgTalentPrestige": 46.628,
    "activeProjects": 0,
    "completedProjects": 2,
    "retiredCount": 10,
    "bankruptcyCount": 0
  },
  {
    "week": 135,
    "playerCash": -263285334,
    "rivalAvgCash": 171421320.50349382,
    "totalSystemCash": 1450927871.034938,
    "totalMarketSentiment": 50,
    "talentPoolSize": 2500,
    "avgTalentPrestige": 46.628,
    "activeProjects": 0,
    "completedProjects": 2,
    "retiredCount": 10,
    "bankruptcyCount": 0
  },
  {
    "week": 136,
    "playerCash": -266264468,
    "rivalAvgCash": 170886766.88849384,
    "totalSystemCash": 1442603200.8849382,
    "totalMarketSentiment": 50,
    "talentPoolSize": 2500,
    "avgTalentPrestige": 46.628,
    "activeProjects": 0,
    "completedProjects": 2,
    "retiredCount": 10,
    "bankruptcyCount": 0
  },
  {
    "week": 137,
    "playerCash": -269251504,
    "rivalAvgCash": 170352140.0534938,
    "totalSystemCash": 1434269896.534938,
    "totalMarketSentiment": 50,
    "talentPoolSize": 2500,
    "avgTalentPrestige": 46.628,
    "activeProjects": 0,
    "completedProjects": 2,
    "retiredCount": 10,
    "bankruptcyCount": 0
  },
  {
    "week": 138,
    "playerCash": -272245712,
    "rivalAvgCash": 169817443.4584938,
    "totalSystemCash": 1425928722.584938,
    "totalMarketSentiment": 50,
    "talentPoolSize": 2500,
    "avgTalentPrestige": 46.628,
    "activeProjects": 0,
    "completedProjects": 2,
    "retiredCount": 10,
    "bankruptcyCount": 0
  },
  {
    "week": 139,
    "playerCash": -275257850,
    "rivalAvgCash": 169282680.88349384,
    "totalSystemCash": 1417568958.8349383,
    "totalMarketSentiment": 50,
    "talentPoolSize": 2500,
    "avgTalentPrestige": 46.628,
    "activeProjects": 0,
    "completedProjects": 2,
    "retiredCount": 10,
    "bankruptcyCount": 0
  },
  {
    "week": 140,
    "playerCash": -278276662,
    "rivalAvgCash": 168747855.6084938,
    "totalSystemCash": 1409201894.084938,
    "totalMarketSentiment": 50,
    "talentPoolSize": 2500,
    "avgTalentPrestige": 46.628,
    "activeProjects": 0,
    "completedProjects": 2,
    "retiredCount": 10,
    "bankruptcyCount": 0
  },
  {
    "week": 141,
    "playerCash": -281304716,
    "rivalAvgCash": 168212970.51349384,
    "totalSystemCash": 1400824989.1349382,
    "totalMarketSentiment": 50,
    "talentPoolSize": 2500,
    "avgTalentPrestige": 46.628,
    "activeProjects": 0,
    "completedProjects": 2,
    "retiredCount": 10,
    "bankruptcyCount": 0
  },
  {
    "week": 142,
    "playerCash": -284347344,
    "rivalAvgCash": 167678028.71849382,
    "totalSystemCash": 1392432943.1849382,
    "totalMarketSentiment": 50,
    "talentPoolSize": 2500,
    "avgTalentPrestige": 46.628,
    "activeProjects": 0,
    "completedProjects": 2,
    "retiredCount": 10,
    "bankruptcyCount": 0
  },
  {
    "week": 143,
    "playerCash": -287409258,
    "rivalAvgCash": 167143032.9834938,
    "totalSystemCash": 1384021071.834938,
    "totalMarketSentiment": 50,
    "talentPoolSize": 2500,
    "avgTalentPrestige": 46.628,
    "activeProjects": 0,
    "completedProjects": 2,
    "retiredCount": 10,
    "bankruptcyCount": 0
  },
  {
    "week": 144,
    "playerCash": -290479262,
    "rivalAvgCash": 166607985.9484938,
    "totalSystemCash": 1375600597.4849381,
    "totalMarketSentiment": 50,
    "talentPoolSize": 2500,
    "avgTalentPrestige": 46.628,
    "activeProjects": 0,
    "completedProjects": 2,
    "retiredCount": 10,
    "bankruptcyCount": 0
  },
  {
    "week": 145,
    "playerCash": -293570914,
    "rivalAvgCash": 166072890.2334938,
    "totalSystemCash": 1367157988.334938,
    "totalMarketSentiment": 50,
    "talentPoolSize": 2500,
    "avgTalentPrestige": 46.628,
    "activeProjects": 0,
    "completedProjects": 2,
    "retiredCount": 10,
    "bankruptcyCount": 0
  },
  {
    "week": 146,
    "playerCash": -296671530,
    "rivalAvgCash": 165537748.2984938,
    "totalSystemCash": 1358705952.9849381,
    "totalMarketSentiment": 50,
    "talentPoolSize": 2500,
    "avgTalentPrestige": 46.628,
    "activeProjects": 0,
    "completedProjects": 2,
    "retiredCount": 10,
    "bankruptcyCount": 0
  },
  {
    "week": 147,
    "playerCash": -299785042,
    "rivalAvgCash": 165002562.4434938,
    "totalSystemCash": 1350240582.4349382,
    "totalMarketSentiment": 50,
    "talentPoolSize": 2500,
    "avgTalentPrestige": 46.628,
    "activeProjects": 0,
    "completedProjects": 2,
    "retiredCount": 10,
    "bankruptcyCount": 0
  },
  {
    "week": 148,
    "playerCash": -302915678,
    "rivalAvgCash": 164467334.7884938,
    "totalSystemCash": 1341757669.884938,
    "totalMarketSentiment": 50,
    "talentPoolSize": 2500,
    "avgTalentPrestige": 46.628,
    "activeProjects": 0,
    "completedProjects": 2,
    "retiredCount": 10,
    "bankruptcyCount": 0
  },
  {
    "week": 149,
    "playerCash": -306054370,
    "rivalAvgCash": 163932067.61349383,
    "totalSystemCash": 1333266306.1349382,
    "totalMarketSentiment": 50,
    "talentPoolSize": 2500,
    "avgTalentPrestige": 46.628,
    "activeProjects": 0,
    "completedProjects": 2,
    "retiredCount": 10,
    "bankruptcyCount": 0
  },
  {
    "week": 150,
    "playerCash": -309200376,
    "rivalAvgCash": 163396762.87849385,
    "totalSystemCash": 1324767252.7849383,
    "totalMarketSentiment": 50,
    "talentPoolSize": 2500,
    "avgTalentPrestige": 46.628,
    "activeProjects": 0,
    "completedProjects": 2,
    "retiredCount": 10,
    "bankruptcyCount": 0
  },
  {
    "week": 151,
    "playerCash": -312367406,
    "rivalAvgCash": 162861422.36349383,
    "totalSystemCash": 1316246817.6349382,
    "totalMarketSentiment": 50,
    "talentPoolSize": 2500,
    "avgTalentPrestige": 46.628,
    "activeProjects": 0,
    "completedProjects": 2,
    "retiredCount": 10,
    "bankruptcyCount": 0
  },
  {
    "week": 152,
    "playerCash": -315551280,
    "rivalAvgCash": 162326047.88849384,
    "totalSystemCash": 1307709198.8849382,
    "totalMarketSentiment": 50,
    "talentPoolSize": 2500,
    "avgTalentPrestige": 46.628,
    "activeProjects": 0,
    "completedProjects": 2,
    "retiredCount": 10,
    "bankruptcyCount": 0
  },
  {
    "week": 153,
    "playerCash": -318743104,
    "rivalAvgCash": 161790641.09349382,
    "totalSystemCash": 1299163306.9349382,
    "totalMarketSentiment": 50,
    "talentPoolSize": 2500,
    "avgTalentPrestige": 46.628,
    "activeProjects": 0,
    "completedProjects": 2,
    "retiredCount": 10,
    "bankruptcyCount": 0
  },
  {
    "week": 154,
    "playerCash": -321955318,
    "rivalAvgCash": 161255203.6984938,
    "totalSystemCash": 1290596718.9849381,
    "totalMarketSentiment": 50,
    "talentPoolSize": 2500,
    "avgTalentPrestige": 46.628,
    "activeProjects": 0,
    "completedProjects": 2,
    "retiredCount": 10,
    "bankruptcyCount": 0
  },
  {
    "week": 155,
    "playerCash": -325176542,
    "rivalAvgCash": 160719737.1634938,
    "totalSystemCash": 1282020829.6349382,
    "totalMarketSentiment": 50,
    "talentPoolSize": 2500,
    "avgTalentPrestige": 46.628,
    "activeProjects": 0,
    "completedProjects": 2,
    "retiredCount": 10,
    "bankruptcyCount": 0
  },
  {
    "week": 156,
    "playerCash": -328406320,
    "rivalAvgCash": 160184242.9884938,
    "totalSystemCash": 1273436109.884938,
    "totalMarketSentiment": 50,
    "talentPoolSize": 2500,
    "avgTalentPrestige": 46.628,
    "activeProjects": 0,
    "completedProjects": 2,
    "retiredCount": 10,
    "bankruptcyCount": 0
  },
  {
    "week": 157,
    "playerCash": -331648146,
    "rivalAvgCash": 159648722.57349378,
    "totalSystemCash": 1264839079.734938,
    "totalMarketSentiment": 50,
    "talentPoolSize": 2500,
    "avgTalentPrestige": 46.628,
    "activeProjects": 0,
    "completedProjects": 2,
    "retiredCount": 10,
    "bankruptcyCount": 0
  },
  {
    "week": 158,
    "playerCash": -334898234,
    "rivalAvgCash": 159113177.1384938,
    "totalSystemCash": 1256233537.384938,
    "totalMarketSentiment": 50,
    "talentPoolSize": 2500,
    "avgTalentPrestige": 46.628,
    "activeProjects": 0,
    "completedProjects": 2,
    "retiredCount": 10,
    "bankruptcyCount": 0
  },
  {
    "week": 159,
    "playerCash": -338156396,
    "rivalAvgCash": 158577607.9234938,
    "totalSystemCash": 1247619683.2349381,
    "totalMarketSentiment": 50,
    "talentPoolSize": 2500,
    "avgTalentPrestige": 46.628,
    "activeProjects": 0,
    "completedProjects": 2,
    "retiredCount": 10,
    "bankruptcyCount": 0
  },
  {
    "week": 160,
    "playerCash": -341433386,
    "rivalAvgCash": 158042016.1684938,
    "totalSystemCash": 1238986775.6849382,
    "totalMarketSentiment": 50,
    "talentPoolSize": 2500,
    "avgTalentPrestige": 46.628,
    "activeProjects": 0,
    "completedProjects": 2,
    "retiredCount": 10,
    "bankruptcyCount": 0
  },
  {
    "week": 161,
    "playerCash": -344718414,
    "rivalAvgCash": 157506402.9934938,
    "totalSystemCash": 1230345615.934938,
    "totalMarketSentiment": 50,
    "talentPoolSize": 2500,
    "avgTalentPrestige": 46.6116,
    "activeProjects": 0,
    "completedProjects": 4,
    "retiredCount": 11,
    "bankruptcyCount": 0
  },
  {
    "week": 162,
    "playerCash": -348021832,
    "rivalAvgCash": 156970769.4584938,
    "totalSystemCash": 1221685862.584938,
    "totalMarketSentiment": 50,
    "talentPoolSize": 2500,
    "avgTalentPrestige": 46.6116,
    "activeProjects": 0,
    "completedProjects": 4,
    "retiredCount": 11,
    "bankruptcyCount": 0
  },
  {
    "week": 163,
    "playerCash": -351338334,
    "rivalAvgCash": 156435116.5834938,
    "totalSystemCash": 1213012831.834938,
    "totalMarketSentiment": 50,
    "talentPoolSize": 2500,
    "avgTalentPrestige": 46.6116,
    "activeProjects": 0,
    "completedProjects": 4,
    "retiredCount": 11,
    "bankruptcyCount": 0
  },
  {
    "week": 164,
    "playerCash": -354673184,
    "rivalAvgCash": 155899445.40849382,
    "totalSystemCash": 1204321270.084938,
    "totalMarketSentiment": 50,
    "talentPoolSize": 2500,
    "avgTalentPrestige": 46.626,
    "activeProjects": 0,
    "completedProjects": 4,
    "retiredCount": 12,
    "bankruptcyCount": 0
  },
  {
    "week": 165,
    "playerCash": -358031256,
    "rivalAvgCash": 155363756.77349383,
    "totalSystemCash": 1195606311.7349381,
    "totalMarketSentiment": 50,
    "talentPoolSize": 2500,
    "avgTalentPrestige": 46.626,
    "activeProjects": 0,
    "completedProjects": 4,
    "retiredCount": 12,
    "bankruptcyCount": 0
  },
  {
    "week": 166,
    "playerCash": -361395276,
    "rivalAvgCash": 154828051.59849378,
    "totalSystemCash": 1186885239.984938,
    "totalMarketSentiment": 50,
    "talentPoolSize": 2500,
    "avgTalentPrestige": 46.626,
    "activeProjects": 0,
    "completedProjects": 4,
    "retiredCount": 12,
    "bankruptcyCount": 0
  },
  {
    "week": 167,
    "playerCash": -364781090,
    "rivalAvgCash": 154292330.6634938,
    "totalSystemCash": 1178142216.6349382,
    "totalMarketSentiment": 50,
    "talentPoolSize": 2500,
    "avgTalentPrestige": 46.626,
    "activeProjects": 0,
    "completedProjects": 4,
    "retiredCount": 12,
    "bankruptcyCount": 0
  },
  {
    "week": 168,
    "playerCash": -368179102,
    "rivalAvgCash": 153756594.74849382,
    "totalSystemCash": 1169386845.4849381,
    "totalMarketSentiment": 50,
    "talentPoolSize": 2500,
    "avgTalentPrestige": 46.626,
    "activeProjects": 0,
    "completedProjects": 4,
    "retiredCount": 12,
    "bankruptcyCount": 0
  },
  {
    "week": 169,
    "playerCash": -371590634,
    "rivalAvgCash": 153220844.61349383,
    "totalSystemCash": 1160617812.1349382,
    "totalMarketSentiment": 50,
    "talentPoolSize": 2500,
    "avgTalentPrestige": 46.622,
    "activeProjects": 0,
    "completedProjects": 4,
    "retiredCount": 13,
    "bankruptcyCount": 0
  },
  {
    "week": 170,
    "playerCash": -375011838,
    "rivalAvgCash": 152685080.9784938,
    "totalSystemCash": 1151838971.784938,
    "totalMarketSentiment": 50,
    "talentPoolSize": 2500,
    "avgTalentPrestige": 46.622,
    "activeProjects": 0,
    "completedProjects": 4,
    "retiredCount": 13,
    "bankruptcyCount": 0
  },
  {
    "week": 171,
    "playerCash": -378458964,
    "rivalAvgCash": 152149304.52349383,
    "totalSystemCash": 1143034081.2349381,
    "totalMarketSentiment": 50,
    "talentPoolSize": 2500,
    "avgTalentPrestige": 46.622,
    "activeProjects": 0,
    "completedProjects": 4,
    "retiredCount": 13,
    "bankruptcyCount": 0
  },
  {
    "week": 172,
    "playerCash": -381917932,
    "rivalAvgCash": 151613515.88849384,
    "totalSystemCash": 1134217226.8849382,
    "totalMarketSentiment": 50,
    "talentPoolSize": 2500,
    "avgTalentPrestige": 46.622,
    "activeProjects": 0,
    "completedProjects": 4,
    "retiredCount": 13,
    "bankruptcyCount": 0
  },
  {
    "week": 173,
    "playerCash": -385386190,
    "rivalAvgCash": 151077715.6934938,
    "totalSystemCash": 1125390966.9349382,
    "totalMarketSentiment": 50,
    "talentPoolSize": 2500,
    "avgTalentPrestige": 46.6224,
    "activeProjects": 0,
    "completedProjects": 4,
    "retiredCount": 14,
    "bankruptcyCount": 0
  },
  {
    "week": 174,
    "playerCash": -388873452,
    "rivalAvgCash": 150541904.49849382,
    "totalSystemCash": 1116545592.9849381,
    "totalMarketSentiment": 50,
    "talentPoolSize": 2500,
    "avgTalentPrestige": 46.6224,
    "activeProjects": 0,
    "completedProjects": 4,
    "retiredCount": 14,
    "bankruptcyCount": 0
  },
  {
    "week": 175,
    "playerCash": -392370058,
    "rivalAvgCash": 150006082.86349383,
    "totalSystemCash": 1107690770.6349382,
    "totalMarketSentiment": 50,
    "talentPoolSize": 2500,
    "avgTalentPrestige": 46.6224,
    "activeProjects": 0,
    "completedProjects": 4,
    "retiredCount": 14,
    "bankruptcyCount": 0
  },
  {
    "week": 176,
    "playerCash": -395876214,
    "rivalAvgCash": 149470251.30849382,
    "totalSystemCash": 1098826299.0849383,
    "totalMarketSentiment": 50,
    "talentPoolSize": 2500,
    "avgTalentPrestige": 46.6224,
    "activeProjects": 0,
    "completedProjects": 4,
    "retiredCount": 14,
    "bankruptcyCount": 0
  },
  {
    "week": 177,
    "playerCash": -399403598,
    "rivalAvgCash": 148934410.31349382,
    "totalSystemCash": 1089940505.1349382,
    "totalMarketSentiment": 50,
    "talentPoolSize": 2500,
    "avgTalentPrestige": 46.6224,
    "activeProjects": 0,
    "completedProjects": 4,
    "retiredCount": 14,
    "bankruptcyCount": 0
  },
  {
    "week": 178,
    "playerCash": -402953560,
    "rivalAvgCash": 148398560.33849382,
    "totalSystemCash": 1081032043.3849382,
    "totalMarketSentiment": 50,
    "talentPoolSize": 2500,
    "avgTalentPrestige": 46.6224,
    "activeProjects": 0,
    "completedProjects": 4,
    "retiredCount": 14,
    "bankruptcyCount": 0
  },
  {
    "week": 179,
    "playerCash": -406512938,
    "rivalAvgCash": 147862701.86349383,
    "totalSystemCash": 1072114080.6349382,
    "totalMarketSentiment": 50,
    "talentPoolSize": 2500,
    "avgTalentPrestige": 46.6224,
    "activeProjects": 0,
    "completedProjects": 4,
    "retiredCount": 14,
    "bankruptcyCount": 0
  },
  {
    "week": 180,
    "playerCash": -410097224,
    "rivalAvgCash": 147326835.26849383,
    "totalSystemCash": 1063171128.6849384,
    "totalMarketSentiment": 50,
    "talentPoolSize": 2500,
    "avgTalentPrestige": 46.6224,
    "activeProjects": 0,
    "completedProjects": 4,
    "retiredCount": 14,
    "bankruptcyCount": 0
  },
  {
    "week": 181,
    "playerCash": -413706632,
    "rivalAvgCash": 146790960.9734938,
    "totalSystemCash": 1054202977.7349381,
    "totalMarketSentiment": 50,
    "talentPoolSize": 2500,
    "avgTalentPrestige": 46.6224,
    "activeProjects": 0,
    "completedProjects": 4,
    "retiredCount": 14,
    "bankruptcyCount": 0
  },
  {
    "week": 182,
    "playerCash": -417335056,
    "rivalAvgCash": 146255079.39849383,
    "totalSystemCash": 1045215737.9849381,
    "totalMarketSentiment": 50,
    "talentPoolSize": 2500,
    "avgTalentPrestige": 46.6224,
    "activeProjects": 0,
    "completedProjects": 4,
    "retiredCount": 14,
    "bankruptcyCount": 0
  },
  {
    "week": 183,
    "playerCash": -420991792,
    "rivalAvgCash": 145719190.88349384,
    "totalSystemCash": 1036200116.8349383,
    "totalMarketSentiment": 50,
    "talentPoolSize": 2500,
    "avgTalentPrestige": 46.6224,
    "activeProjects": 0,
    "completedProjects": 4,
    "retiredCount": 14,
    "bankruptcyCount": 0
  },
  {
    "week": 184,
    "playerCash": -424672642,
    "rivalAvgCash": 145183295.7884938,
    "totalSystemCash": 1027160315.8849382,
    "totalMarketSentiment": 50,
    "talentPoolSize": 2500,
    "avgTalentPrestige": 46.6224,
    "activeProjects": 0,
    "completedProjects": 4,
    "retiredCount": 14,
    "bankruptcyCount": 0
  },
  {
    "week": 185,
    "playerCash": -428376442,
    "rivalAvgCash": 144647394.45349383,
    "totalSystemCash": 1018097502.5349383,
    "totalMarketSentiment": 50,
    "talentPoolSize": 2500,
    "avgTalentPrestige": 46.6224,
    "activeProjects": 0,
    "completedProjects": 4,
    "retiredCount": 14,
    "bankruptcyCount": 0
  },
  {
    "week": 186,
    "playerCash": -432103864,
    "rivalAvgCash": 135411300.15849382,
    "totalSystemCash": 922009137.5849383,
    "totalMarketSentiment": 50,
    "talentPoolSize": 2500,
    "avgTalentPrestige": 46.6224,
    "activeProjects": 0,
    "completedProjects": 4,
    "retiredCount": 14,
    "bankruptcyCount": 0
  },
  {
    "week": 187,
    "playerCash": -435847970,
    "rivalAvgCash": 134621332.57849383,
    "totalSystemCash": 910365355.7849383,
    "totalMarketSentiment": 50,
    "talentPoolSize": 2500,
    "avgTalentPrestige": 46.6224,
    "activeProjects": 0,
    "completedProjects": 4,
    "retiredCount": 14,
    "bankruptcyCount": 0
  },
  {
    "week": 188,
    "playerCash": -439622194,
    "rivalAvgCash": 133831359.17849381,
    "totalSystemCash": 898691397.7849381,
    "totalMarketSentiment": 50,
    "talentPoolSize": 2500,
    "avgTalentPrestige": 46.6224,
    "activeProjects": 0,
    "completedProjects": 4,
    "retiredCount": 14,
    "bankruptcyCount": 0
  },
  {
    "week": 189,
    "playerCash": -443407564,
    "rivalAvgCash": 133041380.25849381,
    "totalSystemCash": 887006238.584938,
    "totalMarketSentiment": 50,
    "talentPoolSize": 2500,
    "avgTalentPrestige": 46.6224,
    "activeProjects": 0,
    "completedProjects": 4,
    "retiredCount": 14,
    "bankruptcyCount": 0
  },
  {
    "week": 190,
    "playerCash": -447214346,
    "rivalAvgCash": 132251396.09849381,
    "totalSystemCash": 875299614.9849381,
    "totalMarketSentiment": 50,
    "talentPoolSize": 2500,
    "avgTalentPrestige": 46.6224,
    "activeProjects": 0,
    "completedProjects": 4,
    "retiredCount": 14,
    "bankruptcyCount": 0
  },
  {
    "week": 191,
    "playerCash": -451026526,
    "rivalAvgCash": 131461406.9384938,
    "totalSystemCash": 863587543.384938,
    "totalMarketSentiment": 50,
    "talentPoolSize": 2500,
    "avgTalentPrestige": 46.6224,
    "activeProjects": 0,
    "completedProjects": 4,
    "retiredCount": 14,
    "bankruptcyCount": 0
  },
  {
    "week": 192,
    "playerCash": -454846556,
    "rivalAvgCash": 130671413.05849381,
    "totalSystemCash": 851867574.584938,
    "totalMarketSentiment": 50,
    "talentPoolSize": 2500,
    "avgTalentPrestige": 46.6224,
    "activeProjects": 0,
    "completedProjects": 4,
    "retiredCount": 14,
    "bankruptcyCount": 0
  },
  {
    "week": 193,
    "playerCash": -458695006,
    "rivalAvgCash": 129881414.69849381,
    "totalSystemCash": 840119140.9849381,
    "totalMarketSentiment": 50,
    "talentPoolSize": 2500,
    "avgTalentPrestige": 46.6224,
    "activeProjects": 0,
    "completedProjects": 4,
    "retiredCount": 14,
    "bankruptcyCount": 0
  },
  {
    "week": 194,
    "playerCash": -462558306,
    "rivalAvgCash": 129091412.09849381,
    "totalSystemCash": 828355814.9849381,
    "totalMarketSentiment": 50,
    "talentPoolSize": 2500,
    "avgTalentPrestige": 46.63,
    "activeProjects": 0,
    "completedProjects": 4,
    "retiredCount": 15,
    "bankruptcyCount": 0
  },
  {
    "week": 195,
    "playerCash": -466443066,
    "rivalAvgCash": 128301405.47849381,
    "totalSystemCash": 816570988.7849381,
    "totalMarketSentiment": 50,
    "talentPoolSize": 2500,
    "avgTalentPrestige": 46.63,
    "activeProjects": 0,
    "completedProjects": 4,
    "retiredCount": 15,
    "bankruptcyCount": 0
  },
  {
    "week": 196,
    "playerCash": -470341326,
    "rivalAvgCash": 127511395.01849382,
    "totalSystemCash": 804772624.1849382,
    "totalMarketSentiment": 50,
    "talentPoolSize": 2500,
    "avgTalentPrestige": 46.63,
    "activeProjects": 0,
    "completedProjects": 4,
    "retiredCount": 15,
    "bankruptcyCount": 0
  },
  {
    "week": 197,
    "playerCash": -474247336,
    "rivalAvgCash": 126721380.93849382,
    "totalSystemCash": 792966473.3849382,
    "totalMarketSentiment": 50,
    "talentPoolSize": 2500,
    "avgTalentPrestige": 46.63,
    "activeProjects": 0,
    "completedProjects": 4,
    "retiredCount": 15,
    "bankruptcyCount": 0
  },
  {
    "week": 198,
    "playerCash": -478180524,
    "rivalAvgCash": 125931363.39849381,
    "totalSystemCash": 781133109.9849381,
    "totalMarketSentiment": 50,
    "talentPoolSize": 2500,
    "avgTalentPrestige": 46.63,
    "activeProjects": 0,
    "completedProjects": 4,
    "retiredCount": 15,
    "bankruptcyCount": 0
  },
  {
    "week": 199,
    "playerCash": -482126450,
    "rivalAvgCash": 125141342.5784938,
    "totalSystemCash": 769286975.7849381,
    "totalMarketSentiment": 50,
    "talentPoolSize": 2500,
    "avgTalentPrestige": 46.63,
    "activeProjects": 0,
    "completedProjects": 4,
    "retiredCount": 15,
    "bankruptcyCount": 0
  },
  {
    "week": 200,
    "playerCash": -486082378,
    "rivalAvgCash": 124351318.67849381,
    "totalSystemCash": 757430808.7849381,
    "totalMarketSentiment": 50,
    "talentPoolSize": 2500,
    "avgTalentPrestige": 46.63,
    "activeProjects": 0,
    "completedProjects": 4,
    "retiredCount": 15,
    "bankruptcyCount": 0
  },
  {
    "week": 201,
    "playerCash": -490053678,
    "rivalAvgCash": 123561291.81849381,
    "totalSystemCash": 745559240.1849382,
    "totalMarketSentiment": 50,
    "talentPoolSize": 2500,
    "avgTalentPrestige": 46.63,
    "activeProjects": 0,
    "completedProjects": 4,
    "retiredCount": 15,
    "bankruptcyCount": 0
  },
  {
    "week": 202,
    "playerCash": -494046124,
    "rivalAvgCash": 122771262.13849382,
    "totalSystemCash": 733666497.3849382,
    "totalMarketSentiment": 50,
    "talentPoolSize": 2500,
    "avgTalentPrestige": 46.63,
    "activeProjects": 0,
    "completedProjects": 4,
    "retiredCount": 15,
    "bankruptcyCount": 0
  },
  {
    "week": 203,
    "playerCash": -498066188,
    "rivalAvgCash": 121981229.83849382,
    "totalSystemCash": 721746110.3849382,
    "totalMarketSentiment": 50,
    "talentPoolSize": 2500,
    "avgTalentPrestige": 46.63,
    "activeProjects": 0,
    "completedProjects": 4,
    "retiredCount": 15,
    "bankruptcyCount": 0
  },
  {
    "week": 204,
    "playerCash": -502113260,
    "rivalAvgCash": 121191195.03849383,
    "totalSystemCash": 709798690.3849382,
    "totalMarketSentiment": 50,
    "talentPoolSize": 2500,
    "avgTalentPrestige": 46.63,
    "activeProjects": 0,
    "completedProjects": 4,
    "retiredCount": 15,
    "bankruptcyCount": 0
  },
  {
    "week": 205,
    "playerCash": -506165046,
    "rivalAvgCash": 120401157.87849383,
    "totalSystemCash": 697846532.7849383,
    "totalMarketSentiment": 50,
    "talentPoolSize": 2500,
    "avgTalentPrestige": 46.63,
    "activeProjects": 0,
    "completedProjects": 4,
    "retiredCount": 15,
    "bankruptcyCount": 0
  },
  {
    "week": 206,
    "playerCash": -510233220,
    "rivalAvgCash": 119611118.4584938,
    "totalSystemCash": 685877964.584938,
    "totalMarketSentiment": 50,
    "talentPoolSize": 2500,
    "avgTalentPrestige": 46.63,
    "activeProjects": 0,
    "completedProjects": 4,
    "retiredCount": 15,
    "bankruptcyCount": 0
  },
  {
    "week": 207,
    "playerCash": -514306518,
    "rivalAvgCash": 118821076.8584938,
    "totalSystemCash": 673904250.584938,
    "totalMarketSentiment": 50,
    "talentPoolSize": 2500,
    "avgTalentPrestige": 46.63,
    "activeProjects": 0,
    "completedProjects": 4,
    "retiredCount": 15,
    "bankruptcyCount": 0
  },
  {
    "week": 208,
    "playerCash": -518392474,
    "rivalAvgCash": 118031033.21849382,
    "totalSystemCash": 661917858.1849382,
    "totalMarketSentiment": 50,
    "talentPoolSize": 2500,
    "avgTalentPrestige": 46.63,
    "activeProjects": 0,
    "completedProjects": 4,
    "retiredCount": 15,
    "bankruptcyCount": 0
  },
  {
    "week": 209,
    "playerCash": -522510550,
    "rivalAvgCash": 117240987.6384938,
    "totalSystemCash": 649899326.384938,
    "totalMarketSentiment": 50,
    "talentPoolSize": 2500,
    "avgTalentPrestige": 46.63,
    "activeProjects": 0,
    "completedProjects": 4,
    "retiredCount": 15,
    "bankruptcyCount": 0
  },
  {
    "week": 210,
    "playerCash": -526644020,
    "rivalAvgCash": 116450940.21849379,
    "totalSystemCash": 637865382.184938,
    "totalMarketSentiment": 50,
    "talentPoolSize": 2500,
    "avgTalentPrestige": 46.63,
    "activeProjects": 0,
    "completedProjects": 4,
    "retiredCount": 15,
    "bankruptcyCount": 0
  },
  {
    "week": 211,
    "playerCash": -530801598,
    "rivalAvgCash": 115660891.0384938,
    "totalSystemCash": 625807312.384938,
    "totalMarketSentiment": 50,
    "talentPoolSize": 2500,
    "avgTalentPrestige": 46.63,
    "activeProjects": 0,
    "completedProjects": 4,
    "retiredCount": 15,
    "bankruptcyCount": 0
  },
  {
    "week": 212,
    "playerCash": -534972040,
    "rivalAvgCash": 114870840.19849381,
    "totalSystemCash": 613736361.9849381,
    "totalMarketSentiment": 50,
    "talentPoolSize": 2500,
    "avgTalentPrestige": 46.63,
    "activeProjects": 0,
    "completedProjects": 4,
    "retiredCount": 15,
    "bankruptcyCount": 0
  },
  {
    "week": 213,
    "playerCash": -539152390,
    "rivalAvgCash": 114080787.7784938,
    "totalSystemCash": 601655487.7849381,
    "totalMarketSentiment": 50,
    "talentPoolSize": 2500,
    "avgTalentPrestige": 46.63,
    "activeProjects": 0,
    "completedProjects": 4,
    "retiredCount": 15,
    "bankruptcyCount": 0
  },
  {
    "week": 214,
    "playerCash": -543363174,
    "rivalAvgCash": 113290733.8584938,
    "totalSystemCash": 589544164.584938,
    "totalMarketSentiment": 50,
    "talentPoolSize": 2500,
    "avgTalentPrestige": 46.63,
    "activeProjects": 0,
    "completedProjects": 4,
    "retiredCount": 15,
    "bankruptcyCount": 0
  },
  {
    "week": 215,
    "playerCash": -547606272,
    "rivalAvgCash": 112500678.5384938,
    "totalSystemCash": 577400513.384938,
    "totalMarketSentiment": 50,
    "talentPoolSize": 2500,
    "avgTalentPrestige": 46.6096,
    "activeProjects": 0,
    "completedProjects": 4,
    "retiredCount": 16,
    "bankruptcyCount": 0
  },
  {
    "week": 216,
    "playerCash": -551866346,
    "rivalAvgCash": 111710621.87849382,
    "totalSystemCash": 565239872.7849381,
    "totalMarketSentiment": 50,
    "talentPoolSize": 2500,
    "avgTalentPrestige": 46.6096,
    "activeProjects": 0,
    "completedProjects": 4,
    "retiredCount": 16,
    "bankruptcyCount": 0
  },
  {
    "week": 217,
    "playerCash": -556136500,
    "rivalAvgCash": 110920563.9584938,
    "totalSystemCash": 553069139.584938,
    "totalMarketSentiment": 50,
    "talentPoolSize": 2500,
    "avgTalentPrestige": 46.6112,
    "activeProjects": 0,
    "completedProjects": 4,
    "retiredCount": 17,
    "bankruptcyCount": 0
  },
  {
    "week": 218,
    "playerCash": -560438462,
    "rivalAvgCash": 110130504.8384938,
    "totalSystemCash": 540866586.384938,
    "totalMarketSentiment": 50,
    "talentPoolSize": 2500,
    "avgTalentPrestige": 46.6112,
    "activeProjects": 0,
    "completedProjects": 4,
    "retiredCount": 17,
    "bankruptcyCount": 0
  },
  {
    "week": 219,
    "playerCash": -564764668,
    "rivalAvgCash": 109340444.5784938,
    "totalSystemCash": 528639777.7849381,
    "totalMarketSentiment": 50,
    "talentPoolSize": 2500,
    "avgTalentPrestige": 46.6112,
    "activeProjects": 0,
    "completedProjects": 4,
    "retiredCount": 17,
    "bankruptcyCount": 0
  },
  {
    "week": 220,
    "playerCash": -569107768,
    "rivalAvgCash": 108550383.2384938,
    "totalSystemCash": 516396064.384938,
    "totalMarketSentiment": 50,
    "talentPoolSize": 2500,
    "avgTalentPrestige": 46.5884,
    "activeProjects": 0,
    "completedProjects": 4,
    "retiredCount": 18,
    "bankruptcyCount": 0
  },
  {
    "week": 221,
    "playerCash": -573480406,
    "rivalAvgCash": 107760320.8584938,
    "totalSystemCash": 504122802.58493805,
    "totalMarketSentiment": 50,
    "talentPoolSize": 2500,
    "avgTalentPrestige": 46.5884,
    "activeProjects": 0,
    "completedProjects": 4,
    "retiredCount": 18,
    "bankruptcyCount": 0
  },
  {
    "week": 222,
    "playerCash": -577870650,
    "rivalAvgCash": 106970257.47849381,
    "totalSystemCash": 491831924.7849381,
    "totalMarketSentiment": 50,
    "talentPoolSize": 2500,
    "avgTalentPrestige": 46.5884,
    "activeProjects": 0,
    "completedProjects": 4,
    "retiredCount": 18,
    "bankruptcyCount": 0
  },
  {
    "week": 223,
    "playerCash": -582297346,
    "rivalAvgCash": 106180193.15849382,
    "totalSystemCash": 479504585.58493817,
    "totalMarketSentiment": 50,
    "talentPoolSize": 2500,
    "avgTalentPrestige": 46.5884,
    "activeProjects": 0,
    "completedProjects": 4,
    "retiredCount": 18,
    "bankruptcyCount": 0
  },
  {
    "week": 224,
    "playerCash": -586758714,
    "rivalAvgCash": 105390127.95849381,
    "totalSystemCash": 467142565.58493817,
    "totalMarketSentiment": 50,
    "talentPoolSize": 2500,
    "avgTalentPrestige": 46.5884,
    "activeProjects": 0,
    "completedProjects": 4,
    "retiredCount": 18,
    "bankruptcyCount": 0
  },
  {
    "week": 225,
    "playerCash": -591235342,
    "rivalAvgCash": 104600061.91849382,
    "totalSystemCash": 454765277.1849382,
    "totalMarketSentiment": 50,
    "talentPoolSize": 2500,
    "avgTalentPrestige": 46.5884,
    "activeProjects": 0,
    "completedProjects": 4,
    "retiredCount": 18,
    "bankruptcyCount": 0
  },
  {
    "week": 226,
    "playerCash": -595745022,
    "rivalAvgCash": 103809995.05849382,
    "totalSystemCash": 442354928.5849383,
    "totalMarketSentiment": 50,
    "talentPoolSize": 2500,
    "avgTalentPrestige": 46.5884,
    "activeProjects": 0,
    "completedProjects": 4,
    "retiredCount": 18,
    "bankruptcyCount": 0
  },
  {
    "week": 227,
    "playerCash": -600260024,
    "rivalAvgCash": 103019927.43849382,
    "totalSystemCash": 429939250.38493824,
    "totalMarketSentiment": 50,
    "talentPoolSize": 2500,
    "avgTalentPrestige": 46.5884,
    "activeProjects": 0,
    "completedProjects": 4,
    "retiredCount": 18,
    "bankruptcyCount": 0
  },
  {
    "week": 228,
    "playerCash": -604812424,
    "rivalAvgCash": 102229859.05849382,
    "totalSystemCash": 417486166.58493817,
    "totalMarketSentiment": 50,
    "talentPoolSize": 2500,
    "avgTalentPrestige": 46.5884,
    "activeProjects": 0,
    "completedProjects": 4,
    "retiredCount": 18,
    "bankruptcyCount": 0
  },
  {
    "week": 229,
    "playerCash": -609383864,
    "rivalAvgCash": 101439789.99849382,
    "totalSystemCash": 405014035.98493826,
    "totalMarketSentiment": 50,
    "talentPoolSize": 2500,
    "avgTalentPrestige": 46.5884,
    "activeProjects": 0,
    "completedProjects": 4,
    "retiredCount": 18,
    "bankruptcyCount": 0
  },
  {
    "week": 230,
    "playerCash": -613985640,
    "rivalAvgCash": 100649720.31849381,
    "totalSystemCash": 392511563.1849381,
    "totalMarketSentiment": 50,
    "talentPoolSize": 2500,
    "avgTalentPrestige": 46.5884,
    "activeProjects": 0,
    "completedProjects": 4,
    "retiredCount": 18,
    "bankruptcyCount": 0
  },
  {
    "week": 231,
    "playerCash": -618619072,
    "rivalAvgCash": 99859650.0184938,
    "totalSystemCash": 379977428.1849381,
    "totalMarketSentiment": 50,
    "talentPoolSize": 2500,
    "avgTalentPrestige": 46.5852,
    "activeProjects": 0,
    "completedProjects": 4,
    "retiredCount": 19,
    "bankruptcyCount": 0
  },
  {
    "week": 232,
    "playerCash": -623275000,
    "rivalAvgCash": 99069579.15849382,
    "totalSystemCash": 367420791.58493817,
    "totalMarketSentiment": 50,
    "talentPoolSize": 2500,
    "avgTalentPrestige": 46.5852,
    "activeProjects": 0,
    "completedProjects": 4,
    "retiredCount": 19,
    "bankruptcyCount": 0
  },
  {
    "week": 233,
    "playerCash": -627937692,
    "rivalAvgCash": 98279507.73849382,
    "totalSystemCash": 354857385.3849381,
    "totalMarketSentiment": 50,
    "talentPoolSize": 2500,
    "avgTalentPrestige": 46.5852,
    "activeProjects": 0,
    "completedProjects": 4,
    "retiredCount": 19,
    "bankruptcyCount": 0
  },
  {
    "week": 234,
    "playerCash": -632632554,
    "rivalAvgCash": 97489435.81849381,
    "totalSystemCash": 342261804.1849382,
    "totalMarketSentiment": 50,
    "talentPoolSize": 2500,
    "avgTalentPrestige": 46.5852,
    "activeProjects": 0,
    "completedProjects": 4,
    "retiredCount": 19,
    "bankruptcyCount": 0
  },
  {
    "week": 235,
    "playerCash": -637353600,
    "rivalAvgCash": 96699363.39849383,
    "totalSystemCash": 329640033.98493826,
    "totalMarketSentiment": 50,
    "talentPoolSize": 2500,
    "avgTalentPrestige": 46.5852,
    "activeProjects": 0,
    "completedProjects": 4,
    "retiredCount": 19,
    "bankruptcyCount": 0
  },
  {
    "week": 236,
    "playerCash": -642093010,
    "rivalAvgCash": 95909290.47849382,
    "totalSystemCash": 316999894.7849382,
    "totalMarketSentiment": 50,
    "talentPoolSize": 2500,
    "avgTalentPrestige": 46.5852,
    "activeProjects": 0,
    "completedProjects": 4,
    "retiredCount": 19,
    "bankruptcyCount": 0
  },
  {
    "week": 237,
    "playerCash": -646849570,
    "rivalAvgCash": 95119217.11849381,
    "totalSystemCash": 304342601.1849381,
    "totalMarketSentiment": 50,
    "talentPoolSize": 2500,
    "avgTalentPrestige": 46.5852,
    "activeProjects": 0,
    "completedProjects": 4,
    "retiredCount": 19,
    "bankruptcyCount": 0
  },
  {
    "week": 238,
    "playerCash": -651620930,
    "rivalAvgCash": 94329143.31849383,
    "totalSystemCash": 291670503.1849383,
    "totalMarketSentiment": 50,
    "talentPoolSize": 2500,
    "avgTalentPrestige": 46.5852,
    "activeProjects": 0,
    "completedProjects": 4,
    "retiredCount": 19,
    "bankruptcyCount": 0
  },
  {
    "week": 239,
    "playerCash": -656396174,
    "rivalAvgCash": 93539069.07849382,
    "totalSystemCash": 278994516.7849382,
    "totalMarketSentiment": 50,
    "talentPoolSize": 2500,
    "avgTalentPrestige": 46.5852,
    "activeProjects": 0,
    "completedProjects": 4,
    "retiredCount": 19,
    "bankruptcyCount": 0
  },
  {
    "week": 240,
    "playerCash": -661180868,
    "rivalAvgCash": 92748994.45849381,
    "totalSystemCash": 266309076.58493817,
    "totalMarketSentiment": 50,
    "talentPoolSize": 2500,
    "avgTalentPrestige": 46.5852,
    "activeProjects": 0,
    "completedProjects": 4,
    "retiredCount": 19,
    "bankruptcyCount": 0
  },
  {
    "week": 241,
    "playerCash": -665992486,
    "rivalAvgCash": 91958919.45849383,
    "totalSystemCash": 253596708.5849383,
    "totalMarketSentiment": 50,
    "talentPoolSize": 2500,
    "avgTalentPrestige": 46.5852,
    "activeProjects": 0,
    "completedProjects": 4,
    "retiredCount": 19,
    "bankruptcyCount": 0
  },
  {
    "week": 242,
    "playerCash": -670812174,
    "rivalAvgCash": 91168844.07849382,
    "totalSystemCash": 240876266.78493822,
    "totalMarketSentiment": 50,
    "talentPoolSize": 2500,
    "avgTalentPrestige": 46.5852,
    "activeProjects": 0,
    "completedProjects": 4,
    "retiredCount": 19,
    "bankruptcyCount": 0
  },
  {
    "week": 243,
    "playerCash": -675657220,
    "rivalAvgCash": 90378768.37849383,
    "totalSystemCash": 228130463.78493834,
    "totalMarketSentiment": 50,
    "talentPoolSize": 2500,
    "avgTalentPrestige": 46.5852,
    "activeProjects": 0,
    "completedProjects": 4,
    "retiredCount": 19,
    "bankruptcyCount": 0
  },
  {
    "week": 244,
    "playerCash": -680538718,
    "rivalAvgCash": 89588692.37849382,
    "totalSystemCash": 215348205.78493822,
    "totalMarketSentiment": 50,
    "talentPoolSize": 2500,
    "avgTalentPrestige": 46.5852,
    "activeProjects": 0,
    "completedProjects": 4,
    "retiredCount": 19,
    "bankruptcyCount": 0
  },
  {
    "week": 245,
    "playerCash": -685452874,
    "rivalAvgCash": 88798616.07849383,
    "totalSystemCash": 202533286.78493834,
    "totalMarketSentiment": 50,
    "talentPoolSize": 2500,
    "avgTalentPrestige": 46.5852,
    "activeProjects": 0,
    "completedProjects": 4,
    "retiredCount": 19,
    "bankruptcyCount": 0
  },
  {
    "week": 246,
    "playerCash": -690381240,
    "rivalAvgCash": 88008539.47849382,
    "totalSystemCash": 189704154.78493822,
    "totalMarketSentiment": 50,
    "talentPoolSize": 2500,
    "avgTalentPrestige": 46.5852,
    "activeProjects": 0,
    "completedProjects": 4,
    "retiredCount": 19,
    "bankruptcyCount": 0
  },
  {
    "week": 247,
    "playerCash": -695314646,
    "rivalAvgCash": 87218462.63849384,
    "totalSystemCash": 176869980.38493836,
    "totalMarketSentiment": 50,
    "talentPoolSize": 2500,
    "avgTalentPrestige": 46.5852,
    "activeProjects": 0,
    "completedProjects": 4,
    "retiredCount": 19,
    "bankruptcyCount": 0
  },
  {
    "week": 248,
    "playerCash": -700256518,
    "rivalAvgCash": 86428385.55849382,
    "totalSystemCash": 164027337.5849383,
    "totalMarketSentiment": 50,
    "talentPoolSize": 2500,
    "avgTalentPrestige": 46.5852,
    "activeProjects": 0,
    "completedProjects": 4,
    "retiredCount": 19,
    "bankruptcyCount": 0
  },
  {
    "week": 249,
    "playerCash": -705236294,
    "rivalAvgCash": 85638308.23849383,
    "totalSystemCash": 151146788.38493824,
    "totalMarketSentiment": 50,
    "talentPoolSize": 2500,
    "avgTalentPrestige": 46.5852,
    "activeProjects": 0,
    "completedProjects": 4,
    "retiredCount": 19,
    "bankruptcyCount": 0
  },
  {
    "week": 250,
    "playerCash": -710251014,
    "rivalAvgCash": 84848230.67849383,
    "totalSystemCash": 138231292.78493834,
    "totalMarketSentiment": 50,
    "talentPoolSize": 2500,
    "avgTalentPrestige": 46.5852,
    "activeProjects": 0,
    "completedProjects": 4,
    "retiredCount": 19,
    "bankruptcyCount": 0
  },
  {
    "week": 251,
    "playerCash": -715289254,
    "rivalAvgCash": 84058152.89849383,
    "totalSystemCash": 125292274.98493826,
    "totalMarketSentiment": 50,
    "talentPoolSize": 2500,
    "avgTalentPrestige": 46.5852,
    "activeProjects": 0,
    "completedProjects": 4,
    "retiredCount": 19,
    "bankruptcyCount": 0
  },
  {
    "week": 252,
    "playerCash": -720362508,
    "rivalAvgCash": 83268074.93849383,
    "totalSystemCash": 112318241.38493836,
    "totalMarketSentiment": 50,
    "talentPoolSize": 2500,
    "avgTalentPrestige": 46.5852,
    "activeProjects": 0,
    "completedProjects": 4,
    "retiredCount": 19,
    "bankruptcyCount": 0
  },
  {
    "week": 253,
    "playerCash": -725467996,
    "rivalAvgCash": 82477996.79849383,
    "totalSystemCash": 99311971.98493826,
    "totalMarketSentiment": 50,
    "talentPoolSize": 2500,
    "avgTalentPrestige": 46.5852,
    "activeProjects": 0,
    "completedProjects": 4,
    "retiredCount": 19,
    "bankruptcyCount": 0
  },
  {
    "week": 254,
    "playerCash": -730605690,
    "rivalAvgCash": 81687918.47849384,
    "totalSystemCash": 86273494.78493834,
    "totalMarketSentiment": 50,
    "talentPoolSize": 2500,
    "avgTalentPrestige": 46.5864,
    "activeProjects": 0,
    "completedProjects": 4,
    "retiredCount": 20,
    "bankruptcyCount": 0
  },
  {
    "week": 255,
    "playerCash": -735761824,
    "rivalAvgCash": 80897839.97849384,
    "totalSystemCash": 73216575.78493834,
    "totalMarketSentiment": 50,
    "talentPoolSize": 2500,
    "avgTalentPrestige": 46.5864,
    "activeProjects": 0,
    "completedProjects": 4,
    "retiredCount": 20,
    "bankruptcyCount": 0
  },
  {
    "week": 256,
    "playerCash": -740928770,
    "rivalAvgCash": 80107761.29849383,
    "totalSystemCash": 60148842.984938264,
    "totalMarketSentiment": 50,
    "talentPoolSize": 2500,
    "avgTalentPrestige": 46.5864,
    "activeProjects": 0,
    "completedProjects": 4,
    "retiredCount": 20,
    "bankruptcyCount": 0
  },
  {
    "week": 257,
    "playerCash": -746137924,
    "rivalAvgCash": 79317682.43849383,
    "totalSystemCash": 47038900.38493836,
    "totalMarketSentiment": 50,
    "talentPoolSize": 2500,
    "avgTalentPrestige": 46.5864,
    "activeProjects": 0,
    "completedProjects": 4,
    "retiredCount": 20,
    "bankruptcyCount": 0
  },
  {
    "week": 258,
    "playerCash": -751384884,
    "rivalAvgCash": 78527603.45849383,
    "totalSystemCash": 33891150.58493829,
    "totalMarketSentiment": 50,
    "talentPoolSize": 2500,
    "avgTalentPrestige": 46.5864,
    "activeProjects": 0,
    "completedProjects": 4,
    "retiredCount": 20,
    "bankruptcyCount": 0
  },
  {
    "week": 259,
    "playerCash": -756652742,
    "rivalAvgCash": 77737524.35849383,
    "totalSystemCash": 20722501.584938288,
    "totalMarketSentiment": 50,
    "talentPoolSize": 2500,
    "avgTalentPrestige": 46.5864,
    "activeProjects": 0,
    "completedProjects": 4,
    "retiredCount": 20,
    "bankruptcyCount": 0
  },
  {
    "week": 260,
    "playerCash": -761955392,
    "rivalAvgCash": 76947445.13849384,
    "totalSystemCash": 7519059.384938359,
    "totalMarketSentiment": 50,
    "talentPoolSize": 2500,
    "avgTalentPrestige": 46.5864,
    "activeProjects": 0,
    "completedProjects": 4,
    "retiredCount": 20,
    "bankruptcyCount": 0
  },
  {
    "week": 261,
    "playerCash": -767303862,
    "rivalAvgCash": 76157365.79849383,
    "totalSystemCash": -5730204.015061736,
    "totalMarketSentiment": 50,
    "talentPoolSize": 2500,
    "avgTalentPrestige": 46.5864,
    "activeProjects": 0,
    "completedProjects": 4,
    "retiredCount": 20,
    "bankruptcyCount": 0
  }
]